Metadata-Version: 2.4
Name: boto3-stubs-lite
Version: 1.42.39
Summary: Lite type annotations for boto3 1.42.39 generated with mypy-boto3-builder 8.12.0
Author-email: Vlad Emelianov <vlad.emelianov.nz@gmail.com>
License-Expression: MIT
Project-URL: Homepage, https://github.com/youtype/mypy_boto3_builder
Project-URL: Documentation, https://youtype.github.io/boto3_stubs_docs/
Project-URL: Source, https://github.com/youtype/mypy_boto3_builder
Project-URL: Tracker, https://github.com/youtype/mypy_boto3_builder/issues
Keywords: boto3,boto3-stubs,type-annotations,mypy,typeshed,autocomplete
Platform: any
Classifier: Development Status :: 5 - Production/Stable
Classifier: Intended Audience :: Developers
Classifier: Environment :: Console
Classifier: Natural Language :: English
Classifier: Operating System :: OS Independent
Classifier: Programming Language :: Python :: 3
Classifier: Programming Language :: Python :: 3.9
Classifier: Programming Language :: Python :: 3.10
Classifier: Programming Language :: Python :: 3.11
Classifier: Programming Language :: Python :: 3.12
Classifier: Programming Language :: Python :: 3.13
Classifier: Programming Language :: Python :: 3.14
Classifier: Programming Language :: Python :: 3 :: Only
Classifier: Programming Language :: Python :: Implementation :: CPython
Classifier: Typing :: Stubs Only
Requires-Python: >=3.9
License-File: LICENSE
Requires-Dist: botocore-stubs
Requires-Dist: types-s3transfer
Requires-Dist: typing-extensions>=4.1.0; python_version < "3.12"
Provides-Extra: full
Requires-Dist: boto3-stubs-full<1.43.0,>=1.42.0; extra == "full"
Provides-Extra: boto3
Requires-Dist: boto3==1.42.39; extra == "boto3"
Provides-Extra: all
Requires-Dist: mypy-boto3-accessanalyzer<1.43.0,>=1.42.0; extra == "all"
Requires-Dist: mypy-boto3-account<1.43.0,>=1.42.0; extra == "all"
Requires-Dist: mypy-boto3-acm<1.43.0,>=1.42.0; extra == "all"
Requires-Dist: mypy-boto3-acm-pca<1.43.0,>=1.42.0; extra == "all"
Requires-Dist: mypy-boto3-aiops<1.43.0,>=1.42.0; extra == "all"
Requires-Dist: mypy-boto3-amp<1.43.0,>=1.42.0; extra == "all"
Requires-Dist: mypy-boto3-amplify<1.43.0,>=1.42.0; extra == "all"
Requires-Dist: mypy-boto3-amplifybackend<1.43.0,>=1.42.0; extra == "all"
Requires-Dist: mypy-boto3-amplifyuibuilder<1.43.0,>=1.42.0; extra == "all"
Requires-Dist: mypy-boto3-apigateway<1.43.0,>=1.42.0; extra == "all"
Requires-Dist: mypy-boto3-apigatewaymanagementapi<1.43.0,>=1.42.0; extra == "all"
Requires-Dist: mypy-boto3-apigatewayv2<1.43.0,>=1.42.0; extra == "all"
Requires-Dist: mypy-boto3-appconfig<1.43.0,>=1.42.0; extra == "all"
Requires-Dist: mypy-boto3-appconfigdata<1.43.0,>=1.42.0; extra == "all"
Requires-Dist: mypy-boto3-appfabric<1.43.0,>=1.42.0; extra == "all"
Requires-Dist: mypy-boto3-appflow<1.43.0,>=1.42.0; extra == "all"
Requires-Dist: mypy-boto3-appintegrations<1.43.0,>=1.42.0; extra == "all"
Requires-Dist: mypy-boto3-application-autoscaling<1.43.0,>=1.42.0; extra == "all"
Requires-Dist: mypy-boto3-application-insights<1.43.0,>=1.42.0; extra == "all"
Requires-Dist: mypy-boto3-application-signals<1.43.0,>=1.42.0; extra == "all"
Requires-Dist: mypy-boto3-applicationcostprofiler<1.43.0,>=1.42.0; extra == "all"
Requires-Dist: mypy-boto3-appmesh<1.43.0,>=1.42.0; extra == "all"
Requires-Dist: mypy-boto3-apprunner<1.43.0,>=1.42.0; extra == "all"
Requires-Dist: mypy-boto3-appstream<1.43.0,>=1.42.0; extra == "all"
Requires-Dist: mypy-boto3-appsync<1.43.0,>=1.42.0; extra == "all"
Requires-Dist: mypy-boto3-arc-region-switch<1.43.0,>=1.42.0; extra == "all"
Requires-Dist: mypy-boto3-arc-zonal-shift<1.43.0,>=1.42.0; extra == "all"
Requires-Dist: mypy-boto3-artifact<1.43.0,>=1.42.0; extra == "all"
Requires-Dist: mypy-boto3-athena<1.43.0,>=1.42.0; extra == "all"
Requires-Dist: mypy-boto3-auditmanager<1.43.0,>=1.42.0; extra == "all"
Requires-Dist: mypy-boto3-autoscaling<1.43.0,>=1.42.0; extra == "all"
Requires-Dist: mypy-boto3-autoscaling-plans<1.43.0,>=1.42.0; extra == "all"
Requires-Dist: mypy-boto3-b2bi<1.43.0,>=1.42.0; extra == "all"
Requires-Dist: mypy-boto3-backup<1.43.0,>=1.42.0; extra == "all"
Requires-Dist: mypy-boto3-backup-gateway<1.43.0,>=1.42.0; extra == "all"
Requires-Dist: mypy-boto3-backupsearch<1.43.0,>=1.42.0; extra == "all"
Requires-Dist: mypy-boto3-batch<1.43.0,>=1.42.0; extra == "all"
Requires-Dist: mypy-boto3-bcm-dashboards<1.43.0,>=1.42.0; extra == "all"
Requires-Dist: mypy-boto3-bcm-data-exports<1.43.0,>=1.42.0; extra == "all"
Requires-Dist: mypy-boto3-bcm-pricing-calculator<1.43.0,>=1.42.0; extra == "all"
Requires-Dist: mypy-boto3-bcm-recommended-actions<1.43.0,>=1.42.0; extra == "all"
Requires-Dist: mypy-boto3-bedrock<1.43.0,>=1.42.0; extra == "all"
Requires-Dist: mypy-boto3-bedrock-agent<1.43.0,>=1.42.0; extra == "all"
Requires-Dist: mypy-boto3-bedrock-agent-runtime<1.43.0,>=1.42.0; extra == "all"
Requires-Dist: mypy-boto3-bedrock-agentcore<1.43.0,>=1.42.0; extra == "all"
Requires-Dist: mypy-boto3-bedrock-agentcore-control<1.43.0,>=1.42.0; extra == "all"
Requires-Dist: mypy-boto3-bedrock-data-automation<1.43.0,>=1.42.0; extra == "all"
Requires-Dist: mypy-boto3-bedrock-data-automation-runtime<1.43.0,>=1.42.0; extra == "all"
Requires-Dist: mypy-boto3-bedrock-runtime<1.43.0,>=1.42.0; extra == "all"
Requires-Dist: mypy-boto3-billing<1.43.0,>=1.42.0; extra == "all"
Requires-Dist: mypy-boto3-billingconductor<1.43.0,>=1.42.0; extra == "all"
Requires-Dist: mypy-boto3-braket<1.43.0,>=1.42.0; extra == "all"
Requires-Dist: mypy-boto3-budgets<1.43.0,>=1.42.0; extra == "all"
Requires-Dist: mypy-boto3-ce<1.43.0,>=1.42.0; extra == "all"
Requires-Dist: mypy-boto3-chatbot<1.43.0,>=1.42.0; extra == "all"
Requires-Dist: mypy-boto3-chime<1.43.0,>=1.42.0; extra == "all"
Requires-Dist: mypy-boto3-chime-sdk-identity<1.43.0,>=1.42.0; extra == "all"
Requires-Dist: mypy-boto3-chime-sdk-media-pipelines<1.43.0,>=1.42.0; extra == "all"
Requires-Dist: mypy-boto3-chime-sdk-meetings<1.43.0,>=1.42.0; extra == "all"
Requires-Dist: mypy-boto3-chime-sdk-messaging<1.43.0,>=1.42.0; extra == "all"
Requires-Dist: mypy-boto3-chime-sdk-voice<1.43.0,>=1.42.0; extra == "all"
Requires-Dist: mypy-boto3-cleanrooms<1.43.0,>=1.42.0; extra == "all"
Requires-Dist: mypy-boto3-cleanroomsml<1.43.0,>=1.42.0; extra == "all"
Requires-Dist: mypy-boto3-cloud9<1.43.0,>=1.42.0; extra == "all"
Requires-Dist: mypy-boto3-cloudcontrol<1.43.0,>=1.42.0; extra == "all"
Requires-Dist: mypy-boto3-clouddirectory<1.43.0,>=1.42.0; extra == "all"
Requires-Dist: mypy-boto3-cloudformation<1.43.0,>=1.42.0; extra == "all"
Requires-Dist: mypy-boto3-cloudfront<1.43.0,>=1.42.0; extra == "all"
Requires-Dist: mypy-boto3-cloudfront-keyvaluestore<1.43.0,>=1.42.0; extra == "all"
Requires-Dist: mypy-boto3-cloudhsm<1.43.0,>=1.42.0; extra == "all"
Requires-Dist: mypy-boto3-cloudhsmv2<1.43.0,>=1.42.0; extra == "all"
Requires-Dist: mypy-boto3-cloudsearch<1.43.0,>=1.42.0; extra == "all"
Requires-Dist: mypy-boto3-cloudsearchdomain<1.43.0,>=1.42.0; extra == "all"
Requires-Dist: mypy-boto3-cloudtrail<1.43.0,>=1.42.0; extra == "all"
Requires-Dist: mypy-boto3-cloudtrail-data<1.43.0,>=1.42.0; extra == "all"
Requires-Dist: mypy-boto3-cloudwatch<1.43.0,>=1.42.0; extra == "all"
Requires-Dist: mypy-boto3-codeartifact<1.43.0,>=1.42.0; extra == "all"
Requires-Dist: mypy-boto3-codebuild<1.43.0,>=1.42.0; extra == "all"
Requires-Dist: mypy-boto3-codecatalyst<1.43.0,>=1.42.0; extra == "all"
Requires-Dist: mypy-boto3-codecommit<1.43.0,>=1.42.0; extra == "all"
Requires-Dist: mypy-boto3-codeconnections<1.43.0,>=1.42.0; extra == "all"
Requires-Dist: mypy-boto3-codedeploy<1.43.0,>=1.42.0; extra == "all"
Requires-Dist: mypy-boto3-codeguru-reviewer<1.43.0,>=1.42.0; extra == "all"
Requires-Dist: mypy-boto3-codeguru-security<1.43.0,>=1.42.0; extra == "all"
Requires-Dist: mypy-boto3-codeguruprofiler<1.43.0,>=1.42.0; extra == "all"
Requires-Dist: mypy-boto3-codepipeline<1.43.0,>=1.42.0; extra == "all"
Requires-Dist: mypy-boto3-codestar-connections<1.43.0,>=1.42.0; extra == "all"
Requires-Dist: mypy-boto3-codestar-notifications<1.43.0,>=1.42.0; extra == "all"
Requires-Dist: mypy-boto3-cognito-identity<1.43.0,>=1.42.0; extra == "all"
Requires-Dist: mypy-boto3-cognito-idp<1.43.0,>=1.42.0; extra == "all"
Requires-Dist: mypy-boto3-cognito-sync<1.43.0,>=1.42.0; extra == "all"
Requires-Dist: mypy-boto3-comprehend<1.43.0,>=1.42.0; extra == "all"
Requires-Dist: mypy-boto3-comprehendmedical<1.43.0,>=1.42.0; extra == "all"
Requires-Dist: mypy-boto3-compute-optimizer<1.43.0,>=1.42.0; extra == "all"
Requires-Dist: mypy-boto3-compute-optimizer-automation<1.43.0,>=1.42.0; extra == "all"
Requires-Dist: mypy-boto3-config<1.43.0,>=1.42.0; extra == "all"
Requires-Dist: mypy-boto3-connect<1.43.0,>=1.42.0; extra == "all"
Requires-Dist: mypy-boto3-connect-contact-lens<1.43.0,>=1.42.0; extra == "all"
Requires-Dist: mypy-boto3-connectcampaigns<1.43.0,>=1.42.0; extra == "all"
Requires-Dist: mypy-boto3-connectcampaignsv2<1.43.0,>=1.42.0; extra == "all"
Requires-Dist: mypy-boto3-connectcases<1.43.0,>=1.42.0; extra == "all"
Requires-Dist: mypy-boto3-connectparticipant<1.43.0,>=1.42.0; extra == "all"
Requires-Dist: mypy-boto3-controlcatalog<1.43.0,>=1.42.0; extra == "all"
Requires-Dist: mypy-boto3-controltower<1.43.0,>=1.42.0; extra == "all"
Requires-Dist: mypy-boto3-cost-optimization-hub<1.43.0,>=1.42.0; extra == "all"
Requires-Dist: mypy-boto3-cur<1.43.0,>=1.42.0; extra == "all"
Requires-Dist: mypy-boto3-customer-profiles<1.43.0,>=1.42.0; extra == "all"
Requires-Dist: mypy-boto3-databrew<1.43.0,>=1.42.0; extra == "all"
Requires-Dist: mypy-boto3-dataexchange<1.43.0,>=1.42.0; extra == "all"
Requires-Dist: mypy-boto3-datapipeline<1.43.0,>=1.42.0; extra == "all"
Requires-Dist: mypy-boto3-datasync<1.43.0,>=1.42.0; extra == "all"
Requires-Dist: mypy-boto3-datazone<1.43.0,>=1.42.0; extra == "all"
Requires-Dist: mypy-boto3-dax<1.43.0,>=1.42.0; extra == "all"
Requires-Dist: mypy-boto3-deadline<1.43.0,>=1.42.0; extra == "all"
Requires-Dist: mypy-boto3-detective<1.43.0,>=1.42.0; extra == "all"
Requires-Dist: mypy-boto3-devicefarm<1.43.0,>=1.42.0; extra == "all"
Requires-Dist: mypy-boto3-devops-guru<1.43.0,>=1.42.0; extra == "all"
Requires-Dist: mypy-boto3-directconnect<1.43.0,>=1.42.0; extra == "all"
Requires-Dist: mypy-boto3-discovery<1.43.0,>=1.42.0; extra == "all"
Requires-Dist: mypy-boto3-dlm<1.43.0,>=1.42.0; extra == "all"
Requires-Dist: mypy-boto3-dms<1.43.0,>=1.42.0; extra == "all"
Requires-Dist: mypy-boto3-docdb<1.43.0,>=1.42.0; extra == "all"
Requires-Dist: mypy-boto3-docdb-elastic<1.43.0,>=1.42.0; extra == "all"
Requires-Dist: mypy-boto3-drs<1.43.0,>=1.42.0; extra == "all"
Requires-Dist: mypy-boto3-ds<1.43.0,>=1.42.0; extra == "all"
Requires-Dist: mypy-boto3-ds-data<1.43.0,>=1.42.0; extra == "all"
Requires-Dist: mypy-boto3-dsql<1.43.0,>=1.42.0; extra == "all"
Requires-Dist: mypy-boto3-dynamodb<1.43.0,>=1.42.0; extra == "all"
Requires-Dist: mypy-boto3-dynamodbstreams<1.43.0,>=1.42.0; extra == "all"
Requires-Dist: mypy-boto3-ebs<1.43.0,>=1.42.0; extra == "all"
Requires-Dist: mypy-boto3-ec2<1.43.0,>=1.42.0; extra == "all"
Requires-Dist: mypy-boto3-ec2-instance-connect<1.43.0,>=1.42.0; extra == "all"
Requires-Dist: mypy-boto3-ecr<1.43.0,>=1.42.0; extra == "all"
Requires-Dist: mypy-boto3-ecr-public<1.43.0,>=1.42.0; extra == "all"
Requires-Dist: mypy-boto3-ecs<1.43.0,>=1.42.0; extra == "all"
Requires-Dist: mypy-boto3-efs<1.43.0,>=1.42.0; extra == "all"
Requires-Dist: mypy-boto3-eks<1.43.0,>=1.42.0; extra == "all"
Requires-Dist: mypy-boto3-eks-auth<1.43.0,>=1.42.0; extra == "all"
Requires-Dist: mypy-boto3-elasticache<1.43.0,>=1.42.0; extra == "all"
Requires-Dist: mypy-boto3-elasticbeanstalk<1.43.0,>=1.42.0; extra == "all"
Requires-Dist: mypy-boto3-elb<1.43.0,>=1.42.0; extra == "all"
Requires-Dist: mypy-boto3-elbv2<1.43.0,>=1.42.0; extra == "all"
Requires-Dist: mypy-boto3-emr<1.43.0,>=1.42.0; extra == "all"
Requires-Dist: mypy-boto3-emr-containers<1.43.0,>=1.42.0; extra == "all"
Requires-Dist: mypy-boto3-emr-serverless<1.43.0,>=1.42.0; extra == "all"
Requires-Dist: mypy-boto3-entityresolution<1.43.0,>=1.42.0; extra == "all"
Requires-Dist: mypy-boto3-es<1.43.0,>=1.42.0; extra == "all"
Requires-Dist: mypy-boto3-events<1.43.0,>=1.42.0; extra == "all"
Requires-Dist: mypy-boto3-evidently<1.43.0,>=1.42.0; extra == "all"
Requires-Dist: mypy-boto3-evs<1.43.0,>=1.42.0; extra == "all"
Requires-Dist: mypy-boto3-finspace<1.43.0,>=1.42.0; extra == "all"
Requires-Dist: mypy-boto3-finspace-data<1.43.0,>=1.42.0; extra == "all"
Requires-Dist: mypy-boto3-firehose<1.43.0,>=1.42.0; extra == "all"
Requires-Dist: mypy-boto3-fis<1.43.0,>=1.42.0; extra == "all"
Requires-Dist: mypy-boto3-fms<1.43.0,>=1.42.0; extra == "all"
Requires-Dist: mypy-boto3-forecast<1.43.0,>=1.42.0; extra == "all"
Requires-Dist: mypy-boto3-forecastquery<1.43.0,>=1.42.0; extra == "all"
Requires-Dist: mypy-boto3-frauddetector<1.43.0,>=1.42.0; extra == "all"
Requires-Dist: mypy-boto3-freetier<1.43.0,>=1.42.0; extra == "all"
Requires-Dist: mypy-boto3-fsx<1.43.0,>=1.42.0; extra == "all"
Requires-Dist: mypy-boto3-gamelift<1.43.0,>=1.42.0; extra == "all"
Requires-Dist: mypy-boto3-gameliftstreams<1.43.0,>=1.42.0; extra == "all"
Requires-Dist: mypy-boto3-geo-maps<1.43.0,>=1.42.0; extra == "all"
Requires-Dist: mypy-boto3-geo-places<1.43.0,>=1.42.0; extra == "all"
Requires-Dist: mypy-boto3-geo-routes<1.43.0,>=1.42.0; extra == "all"
Requires-Dist: mypy-boto3-glacier<1.43.0,>=1.42.0; extra == "all"
Requires-Dist: mypy-boto3-globalaccelerator<1.43.0,>=1.42.0; extra == "all"
Requires-Dist: mypy-boto3-glue<1.43.0,>=1.42.0; extra == "all"
Requires-Dist: mypy-boto3-grafana<1.43.0,>=1.42.0; extra == "all"
Requires-Dist: mypy-boto3-greengrass<1.43.0,>=1.42.0; extra == "all"
Requires-Dist: mypy-boto3-greengrassv2<1.43.0,>=1.42.0; extra == "all"
Requires-Dist: mypy-boto3-groundstation<1.43.0,>=1.42.0; extra == "all"
Requires-Dist: mypy-boto3-guardduty<1.43.0,>=1.42.0; extra == "all"
Requires-Dist: mypy-boto3-health<1.43.0,>=1.42.0; extra == "all"
Requires-Dist: mypy-boto3-healthlake<1.43.0,>=1.42.0; extra == "all"
Requires-Dist: mypy-boto3-iam<1.43.0,>=1.42.0; extra == "all"
Requires-Dist: mypy-boto3-identitystore<1.43.0,>=1.42.0; extra == "all"
Requires-Dist: mypy-boto3-imagebuilder<1.43.0,>=1.42.0; extra == "all"
Requires-Dist: mypy-boto3-importexport<1.43.0,>=1.42.0; extra == "all"
Requires-Dist: mypy-boto3-inspector<1.43.0,>=1.42.0; extra == "all"
Requires-Dist: mypy-boto3-inspector-scan<1.43.0,>=1.42.0; extra == "all"
Requires-Dist: mypy-boto3-inspector2<1.43.0,>=1.42.0; extra == "all"
Requires-Dist: mypy-boto3-internetmonitor<1.43.0,>=1.42.0; extra == "all"
Requires-Dist: mypy-boto3-invoicing<1.43.0,>=1.42.0; extra == "all"
Requires-Dist: mypy-boto3-iot<1.43.0,>=1.42.0; extra == "all"
Requires-Dist: mypy-boto3-iot-data<1.43.0,>=1.42.0; extra == "all"
Requires-Dist: mypy-boto3-iot-jobs-data<1.43.0,>=1.42.0; extra == "all"
Requires-Dist: mypy-boto3-iot-managed-integrations<1.43.0,>=1.42.0; extra == "all"
Requires-Dist: mypy-boto3-iotanalytics<1.43.0,>=1.42.0; extra == "all"
Requires-Dist: mypy-boto3-iotdeviceadvisor<1.43.0,>=1.42.0; extra == "all"
Requires-Dist: mypy-boto3-iotevents<1.43.0,>=1.42.0; extra == "all"
Requires-Dist: mypy-boto3-iotevents-data<1.43.0,>=1.42.0; extra == "all"
Requires-Dist: mypy-boto3-iotfleetwise<1.43.0,>=1.42.0; extra == "all"
Requires-Dist: mypy-boto3-iotsecuretunneling<1.43.0,>=1.42.0; extra == "all"
Requires-Dist: mypy-boto3-iotsitewise<1.43.0,>=1.42.0; extra == "all"
Requires-Dist: mypy-boto3-iotthingsgraph<1.43.0,>=1.42.0; extra == "all"
Requires-Dist: mypy-boto3-iottwinmaker<1.43.0,>=1.42.0; extra == "all"
Requires-Dist: mypy-boto3-iotwireless<1.43.0,>=1.42.0; extra == "all"
Requires-Dist: mypy-boto3-ivs<1.43.0,>=1.42.0; extra == "all"
Requires-Dist: mypy-boto3-ivs-realtime<1.43.0,>=1.42.0; extra == "all"
Requires-Dist: mypy-boto3-ivschat<1.43.0,>=1.42.0; extra == "all"
Requires-Dist: mypy-boto3-kafka<1.43.0,>=1.42.0; extra == "all"
Requires-Dist: mypy-boto3-kafkaconnect<1.43.0,>=1.42.0; extra == "all"
Requires-Dist: mypy-boto3-kendra<1.43.0,>=1.42.0; extra == "all"
Requires-Dist: mypy-boto3-kendra-ranking<1.43.0,>=1.42.0; extra == "all"
Requires-Dist: mypy-boto3-keyspaces<1.43.0,>=1.42.0; extra == "all"
Requires-Dist: mypy-boto3-keyspacesstreams<1.43.0,>=1.42.0; extra == "all"
Requires-Dist: mypy-boto3-kinesis<1.43.0,>=1.42.0; extra == "all"
Requires-Dist: mypy-boto3-kinesis-video-archived-media<1.43.0,>=1.42.0; extra == "all"
Requires-Dist: mypy-boto3-kinesis-video-media<1.43.0,>=1.42.0; extra == "all"
Requires-Dist: mypy-boto3-kinesis-video-signaling<1.43.0,>=1.42.0; extra == "all"
Requires-Dist: mypy-boto3-kinesis-video-webrtc-storage<1.43.0,>=1.42.0; extra == "all"
Requires-Dist: mypy-boto3-kinesisanalytics<1.43.0,>=1.42.0; extra == "all"
Requires-Dist: mypy-boto3-kinesisanalyticsv2<1.43.0,>=1.42.0; extra == "all"
Requires-Dist: mypy-boto3-kinesisvideo<1.43.0,>=1.42.0; extra == "all"
Requires-Dist: mypy-boto3-kms<1.43.0,>=1.42.0; extra == "all"
Requires-Dist: mypy-boto3-lakeformation<1.43.0,>=1.42.0; extra == "all"
Requires-Dist: mypy-boto3-lambda<1.43.0,>=1.42.0; extra == "all"
Requires-Dist: mypy-boto3-launch-wizard<1.43.0,>=1.42.0; extra == "all"
Requires-Dist: mypy-boto3-lex-models<1.43.0,>=1.42.0; extra == "all"
Requires-Dist: mypy-boto3-lex-runtime<1.43.0,>=1.42.0; extra == "all"
Requires-Dist: mypy-boto3-lexv2-models<1.43.0,>=1.42.0; extra == "all"
Requires-Dist: mypy-boto3-lexv2-runtime<1.43.0,>=1.42.0; extra == "all"
Requires-Dist: mypy-boto3-license-manager<1.43.0,>=1.42.0; extra == "all"
Requires-Dist: mypy-boto3-license-manager-linux-subscriptions<1.43.0,>=1.42.0; extra == "all"
Requires-Dist: mypy-boto3-license-manager-user-subscriptions<1.43.0,>=1.42.0; extra == "all"
Requires-Dist: mypy-boto3-lightsail<1.43.0,>=1.42.0; extra == "all"
Requires-Dist: mypy-boto3-location<1.43.0,>=1.42.0; extra == "all"
Requires-Dist: mypy-boto3-logs<1.43.0,>=1.42.0; extra == "all"
Requires-Dist: mypy-boto3-lookoutequipment<1.43.0,>=1.42.0; extra == "all"
Requires-Dist: mypy-boto3-m2<1.43.0,>=1.42.0; extra == "all"
Requires-Dist: mypy-boto3-machinelearning<1.43.0,>=1.42.0; extra == "all"
Requires-Dist: mypy-boto3-macie2<1.43.0,>=1.42.0; extra == "all"
Requires-Dist: mypy-boto3-mailmanager<1.43.0,>=1.42.0; extra == "all"
Requires-Dist: mypy-boto3-managedblockchain<1.43.0,>=1.42.0; extra == "all"
Requires-Dist: mypy-boto3-managedblockchain-query<1.43.0,>=1.42.0; extra == "all"
Requires-Dist: mypy-boto3-marketplace-agreement<1.43.0,>=1.42.0; extra == "all"
Requires-Dist: mypy-boto3-marketplace-catalog<1.43.0,>=1.42.0; extra == "all"
Requires-Dist: mypy-boto3-marketplace-deployment<1.43.0,>=1.42.0; extra == "all"
Requires-Dist: mypy-boto3-marketplace-entitlement<1.43.0,>=1.42.0; extra == "all"
Requires-Dist: mypy-boto3-marketplace-reporting<1.43.0,>=1.42.0; extra == "all"
Requires-Dist: mypy-boto3-marketplacecommerceanalytics<1.43.0,>=1.42.0; extra == "all"
Requires-Dist: mypy-boto3-mediaconnect<1.43.0,>=1.42.0; extra == "all"
Requires-Dist: mypy-boto3-mediaconvert<1.43.0,>=1.42.0; extra == "all"
Requires-Dist: mypy-boto3-medialive<1.43.0,>=1.42.0; extra == "all"
Requires-Dist: mypy-boto3-mediapackage<1.43.0,>=1.42.0; extra == "all"
Requires-Dist: mypy-boto3-mediapackage-vod<1.43.0,>=1.42.0; extra == "all"
Requires-Dist: mypy-boto3-mediapackagev2<1.43.0,>=1.42.0; extra == "all"
Requires-Dist: mypy-boto3-mediastore<1.43.0,>=1.42.0; extra == "all"
Requires-Dist: mypy-boto3-mediastore-data<1.43.0,>=1.42.0; extra == "all"
Requires-Dist: mypy-boto3-mediatailor<1.43.0,>=1.42.0; extra == "all"
Requires-Dist: mypy-boto3-medical-imaging<1.43.0,>=1.42.0; extra == "all"
Requires-Dist: mypy-boto3-memorydb<1.43.0,>=1.42.0; extra == "all"
Requires-Dist: mypy-boto3-meteringmarketplace<1.43.0,>=1.42.0; extra == "all"
Requires-Dist: mypy-boto3-mgh<1.43.0,>=1.42.0; extra == "all"
Requires-Dist: mypy-boto3-mgn<1.43.0,>=1.42.0; extra == "all"
Requires-Dist: mypy-boto3-migration-hub-refactor-spaces<1.43.0,>=1.42.0; extra == "all"
Requires-Dist: mypy-boto3-migrationhub-config<1.43.0,>=1.42.0; extra == "all"
Requires-Dist: mypy-boto3-migrationhuborchestrator<1.43.0,>=1.42.0; extra == "all"
Requires-Dist: mypy-boto3-migrationhubstrategy<1.43.0,>=1.42.0; extra == "all"
Requires-Dist: mypy-boto3-mpa<1.43.0,>=1.42.0; extra == "all"
Requires-Dist: mypy-boto3-mq<1.43.0,>=1.42.0; extra == "all"
Requires-Dist: mypy-boto3-mturk<1.43.0,>=1.42.0; extra == "all"
Requires-Dist: mypy-boto3-mwaa<1.43.0,>=1.42.0; extra == "all"
Requires-Dist: mypy-boto3-mwaa-serverless<1.43.0,>=1.42.0; extra == "all"
Requires-Dist: mypy-boto3-neptune<1.43.0,>=1.42.0; extra == "all"
Requires-Dist: mypy-boto3-neptune-graph<1.43.0,>=1.42.0; extra == "all"
Requires-Dist: mypy-boto3-neptunedata<1.43.0,>=1.42.0; extra == "all"
Requires-Dist: mypy-boto3-network-firewall<1.43.0,>=1.42.0; extra == "all"
Requires-Dist: mypy-boto3-networkflowmonitor<1.43.0,>=1.42.0; extra == "all"
Requires-Dist: mypy-boto3-networkmanager<1.43.0,>=1.42.0; extra == "all"
Requires-Dist: mypy-boto3-networkmonitor<1.43.0,>=1.42.0; extra == "all"
Requires-Dist: mypy-boto3-notifications<1.43.0,>=1.42.0; extra == "all"
Requires-Dist: mypy-boto3-notificationscontacts<1.43.0,>=1.42.0; extra == "all"
Requires-Dist: mypy-boto3-nova-act<1.43.0,>=1.42.0; extra == "all"
Requires-Dist: mypy-boto3-oam<1.43.0,>=1.42.0; extra == "all"
Requires-Dist: mypy-boto3-observabilityadmin<1.43.0,>=1.42.0; extra == "all"
Requires-Dist: mypy-boto3-odb<1.43.0,>=1.42.0; extra == "all"
Requires-Dist: mypy-boto3-omics<1.43.0,>=1.42.0; extra == "all"
Requires-Dist: mypy-boto3-opensearch<1.43.0,>=1.42.0; extra == "all"
Requires-Dist: mypy-boto3-opensearchserverless<1.43.0,>=1.42.0; extra == "all"
Requires-Dist: mypy-boto3-organizations<1.43.0,>=1.42.0; extra == "all"
Requires-Dist: mypy-boto3-osis<1.43.0,>=1.42.0; extra == "all"
Requires-Dist: mypy-boto3-outposts<1.43.0,>=1.42.0; extra == "all"
Requires-Dist: mypy-boto3-panorama<1.43.0,>=1.42.0; extra == "all"
Requires-Dist: mypy-boto3-partnercentral-account<1.43.0,>=1.42.0; extra == "all"
Requires-Dist: mypy-boto3-partnercentral-benefits<1.43.0,>=1.42.0; extra == "all"
Requires-Dist: mypy-boto3-partnercentral-channel<1.43.0,>=1.42.0; extra == "all"
Requires-Dist: mypy-boto3-partnercentral-selling<1.43.0,>=1.42.0; extra == "all"
Requires-Dist: mypy-boto3-payment-cryptography<1.43.0,>=1.42.0; extra == "all"
Requires-Dist: mypy-boto3-payment-cryptography-data<1.43.0,>=1.42.0; extra == "all"
Requires-Dist: mypy-boto3-pca-connector-ad<1.43.0,>=1.42.0; extra == "all"
Requires-Dist: mypy-boto3-pca-connector-scep<1.43.0,>=1.42.0; extra == "all"
Requires-Dist: mypy-boto3-pcs<1.43.0,>=1.42.0; extra == "all"
Requires-Dist: mypy-boto3-personalize<1.43.0,>=1.42.0; extra == "all"
Requires-Dist: mypy-boto3-personalize-events<1.43.0,>=1.42.0; extra == "all"
Requires-Dist: mypy-boto3-personalize-runtime<1.43.0,>=1.42.0; extra == "all"
Requires-Dist: mypy-boto3-pi<1.43.0,>=1.42.0; extra == "all"
Requires-Dist: mypy-boto3-pinpoint<1.43.0,>=1.42.0; extra == "all"
Requires-Dist: mypy-boto3-pinpoint-email<1.43.0,>=1.42.0; extra == "all"
Requires-Dist: mypy-boto3-pinpoint-sms-voice<1.43.0,>=1.42.0; extra == "all"
Requires-Dist: mypy-boto3-pinpoint-sms-voice-v2<1.43.0,>=1.42.0; extra == "all"
Requires-Dist: mypy-boto3-pipes<1.43.0,>=1.42.0; extra == "all"
Requires-Dist: mypy-boto3-polly<1.43.0,>=1.42.0; extra == "all"
Requires-Dist: mypy-boto3-pricing<1.43.0,>=1.42.0; extra == "all"
Requires-Dist: mypy-boto3-proton<1.43.0,>=1.42.0; extra == "all"
Requires-Dist: mypy-boto3-qapps<1.43.0,>=1.42.0; extra == "all"
Requires-Dist: mypy-boto3-qbusiness<1.43.0,>=1.42.0; extra == "all"
Requires-Dist: mypy-boto3-qconnect<1.43.0,>=1.42.0; extra == "all"
Requires-Dist: mypy-boto3-quicksight<1.43.0,>=1.42.0; extra == "all"
Requires-Dist: mypy-boto3-ram<1.43.0,>=1.42.0; extra == "all"
Requires-Dist: mypy-boto3-rbin<1.43.0,>=1.42.0; extra == "all"
Requires-Dist: mypy-boto3-rds<1.43.0,>=1.42.0; extra == "all"
Requires-Dist: mypy-boto3-rds-data<1.43.0,>=1.42.0; extra == "all"
Requires-Dist: mypy-boto3-redshift<1.43.0,>=1.42.0; extra == "all"
Requires-Dist: mypy-boto3-redshift-data<1.43.0,>=1.42.0; extra == "all"
Requires-Dist: mypy-boto3-redshift-serverless<1.43.0,>=1.42.0; extra == "all"
Requires-Dist: mypy-boto3-rekognition<1.43.0,>=1.42.0; extra == "all"
Requires-Dist: mypy-boto3-repostspace<1.43.0,>=1.42.0; extra == "all"
Requires-Dist: mypy-boto3-resiliencehub<1.43.0,>=1.42.0; extra == "all"
Requires-Dist: mypy-boto3-resource-explorer-2<1.43.0,>=1.42.0; extra == "all"
Requires-Dist: mypy-boto3-resource-groups<1.43.0,>=1.42.0; extra == "all"
Requires-Dist: mypy-boto3-resourcegroupstaggingapi<1.43.0,>=1.42.0; extra == "all"
Requires-Dist: mypy-boto3-rolesanywhere<1.43.0,>=1.42.0; extra == "all"
Requires-Dist: mypy-boto3-route53<1.43.0,>=1.42.0; extra == "all"
Requires-Dist: mypy-boto3-route53-recovery-cluster<1.43.0,>=1.42.0; extra == "all"
Requires-Dist: mypy-boto3-route53-recovery-control-config<1.43.0,>=1.42.0; extra == "all"
Requires-Dist: mypy-boto3-route53-recovery-readiness<1.43.0,>=1.42.0; extra == "all"
Requires-Dist: mypy-boto3-route53domains<1.43.0,>=1.42.0; extra == "all"
Requires-Dist: mypy-boto3-route53globalresolver<1.43.0,>=1.42.0; extra == "all"
Requires-Dist: mypy-boto3-route53profiles<1.43.0,>=1.42.0; extra == "all"
Requires-Dist: mypy-boto3-route53resolver<1.43.0,>=1.42.0; extra == "all"
Requires-Dist: mypy-boto3-rtbfabric<1.43.0,>=1.42.0; extra == "all"
Requires-Dist: mypy-boto3-rum<1.43.0,>=1.42.0; extra == "all"
Requires-Dist: mypy-boto3-s3<1.43.0,>=1.42.0; extra == "all"
Requires-Dist: mypy-boto3-s3control<1.43.0,>=1.42.0; extra == "all"
Requires-Dist: mypy-boto3-s3outposts<1.43.0,>=1.42.0; extra == "all"
Requires-Dist: mypy-boto3-s3tables<1.43.0,>=1.42.0; extra == "all"
Requires-Dist: mypy-boto3-s3vectors<1.43.0,>=1.42.0; extra == "all"
Requires-Dist: mypy-boto3-sagemaker<1.43.0,>=1.42.0; extra == "all"
Requires-Dist: mypy-boto3-sagemaker-a2i-runtime<1.43.0,>=1.42.0; extra == "all"
Requires-Dist: mypy-boto3-sagemaker-edge<1.43.0,>=1.42.0; extra == "all"
Requires-Dist: mypy-boto3-sagemaker-featurestore-runtime<1.43.0,>=1.42.0; extra == "all"
Requires-Dist: mypy-boto3-sagemaker-geospatial<1.43.0,>=1.42.0; extra == "all"
Requires-Dist: mypy-boto3-sagemaker-metrics<1.43.0,>=1.42.0; extra == "all"
Requires-Dist: mypy-boto3-sagemaker-runtime<1.43.0,>=1.42.0; extra == "all"
Requires-Dist: mypy-boto3-savingsplans<1.43.0,>=1.42.0; extra == "all"
Requires-Dist: mypy-boto3-scheduler<1.43.0,>=1.42.0; extra == "all"
Requires-Dist: mypy-boto3-schemas<1.43.0,>=1.42.0; extra == "all"
Requires-Dist: mypy-boto3-sdb<1.43.0,>=1.42.0; extra == "all"
Requires-Dist: mypy-boto3-secretsmanager<1.43.0,>=1.42.0; extra == "all"
Requires-Dist: mypy-boto3-security-ir<1.43.0,>=1.42.0; extra == "all"
Requires-Dist: mypy-boto3-securityhub<1.43.0,>=1.42.0; extra == "all"
Requires-Dist: mypy-boto3-securitylake<1.43.0,>=1.42.0; extra == "all"
Requires-Dist: mypy-boto3-serverlessrepo<1.43.0,>=1.42.0; extra == "all"
Requires-Dist: mypy-boto3-service-quotas<1.43.0,>=1.42.0; extra == "all"
Requires-Dist: mypy-boto3-servicecatalog<1.43.0,>=1.42.0; extra == "all"
Requires-Dist: mypy-boto3-servicecatalog-appregistry<1.43.0,>=1.42.0; extra == "all"
Requires-Dist: mypy-boto3-servicediscovery<1.43.0,>=1.42.0; extra == "all"
Requires-Dist: mypy-boto3-ses<1.43.0,>=1.42.0; extra == "all"
Requires-Dist: mypy-boto3-sesv2<1.43.0,>=1.42.0; extra == "all"
Requires-Dist: mypy-boto3-shield<1.43.0,>=1.42.0; extra == "all"
Requires-Dist: mypy-boto3-signer<1.43.0,>=1.42.0; extra == "all"
Requires-Dist: mypy-boto3-signin<1.43.0,>=1.42.0; extra == "all"
Requires-Dist: mypy-boto3-simspaceweaver<1.43.0,>=1.42.0; extra == "all"
Requires-Dist: mypy-boto3-snow-device-management<1.43.0,>=1.42.0; extra == "all"
Requires-Dist: mypy-boto3-snowball<1.43.0,>=1.42.0; extra == "all"
Requires-Dist: mypy-boto3-sns<1.43.0,>=1.42.0; extra == "all"
Requires-Dist: mypy-boto3-socialmessaging<1.43.0,>=1.42.0; extra == "all"
Requires-Dist: mypy-boto3-sqs<1.43.0,>=1.42.0; extra == "all"
Requires-Dist: mypy-boto3-ssm<1.43.0,>=1.42.0; extra == "all"
Requires-Dist: mypy-boto3-ssm-contacts<1.43.0,>=1.42.0; extra == "all"
Requires-Dist: mypy-boto3-ssm-guiconnect<1.43.0,>=1.42.0; extra == "all"
Requires-Dist: mypy-boto3-ssm-incidents<1.43.0,>=1.42.0; extra == "all"
Requires-Dist: mypy-boto3-ssm-quicksetup<1.43.0,>=1.42.0; extra == "all"
Requires-Dist: mypy-boto3-ssm-sap<1.43.0,>=1.42.0; extra == "all"
Requires-Dist: mypy-boto3-sso<1.43.0,>=1.42.0; extra == "all"
Requires-Dist: mypy-boto3-sso-admin<1.43.0,>=1.42.0; extra == "all"
Requires-Dist: mypy-boto3-sso-oidc<1.43.0,>=1.42.0; extra == "all"
Requires-Dist: mypy-boto3-stepfunctions<1.43.0,>=1.42.0; extra == "all"
Requires-Dist: mypy-boto3-storagegateway<1.43.0,>=1.42.0; extra == "all"
Requires-Dist: mypy-boto3-sts<1.43.0,>=1.42.0; extra == "all"
Requires-Dist: mypy-boto3-supplychain<1.43.0,>=1.42.0; extra == "all"
Requires-Dist: mypy-boto3-support<1.43.0,>=1.42.0; extra == "all"
Requires-Dist: mypy-boto3-support-app<1.43.0,>=1.42.0; extra == "all"
Requires-Dist: mypy-boto3-swf<1.43.0,>=1.42.0; extra == "all"
Requires-Dist: mypy-boto3-synthetics<1.43.0,>=1.42.0; extra == "all"
Requires-Dist: mypy-boto3-taxsettings<1.43.0,>=1.42.0; extra == "all"
Requires-Dist: mypy-boto3-textract<1.43.0,>=1.42.0; extra == "all"
Requires-Dist: mypy-boto3-timestream-influxdb<1.43.0,>=1.42.0; extra == "all"
Requires-Dist: mypy-boto3-timestream-query<1.43.0,>=1.42.0; extra == "all"
Requires-Dist: mypy-boto3-timestream-write<1.43.0,>=1.42.0; extra == "all"
Requires-Dist: mypy-boto3-tnb<1.43.0,>=1.42.0; extra == "all"
Requires-Dist: mypy-boto3-transcribe<1.43.0,>=1.42.0; extra == "all"
Requires-Dist: mypy-boto3-transfer<1.43.0,>=1.42.0; extra == "all"
Requires-Dist: mypy-boto3-translate<1.43.0,>=1.42.0; extra == "all"
Requires-Dist: mypy-boto3-trustedadvisor<1.43.0,>=1.42.0; extra == "all"
Requires-Dist: mypy-boto3-verifiedpermissions<1.43.0,>=1.42.0; extra == "all"
Requires-Dist: mypy-boto3-voice-id<1.43.0,>=1.42.0; extra == "all"
Requires-Dist: mypy-boto3-vpc-lattice<1.43.0,>=1.42.0; extra == "all"
Requires-Dist: mypy-boto3-waf<1.43.0,>=1.42.0; extra == "all"
Requires-Dist: mypy-boto3-waf-regional<1.43.0,>=1.42.0; extra == "all"
Requires-Dist: mypy-boto3-wafv2<1.43.0,>=1.42.0; extra == "all"
Requires-Dist: mypy-boto3-wellarchitected<1.43.0,>=1.42.0; extra == "all"
Requires-Dist: mypy-boto3-wickr<1.43.0,>=1.42.0; extra == "all"
Requires-Dist: mypy-boto3-wisdom<1.43.0,>=1.42.0; extra == "all"
Requires-Dist: mypy-boto3-workdocs<1.43.0,>=1.42.0; extra == "all"
Requires-Dist: mypy-boto3-workmail<1.43.0,>=1.42.0; extra == "all"
Requires-Dist: mypy-boto3-workmailmessageflow<1.43.0,>=1.42.0; extra == "all"
Requires-Dist: mypy-boto3-workspaces<1.43.0,>=1.42.0; extra == "all"
Requires-Dist: mypy-boto3-workspaces-instances<1.43.0,>=1.42.0; extra == "all"
Requires-Dist: mypy-boto3-workspaces-thin-client<1.43.0,>=1.42.0; extra == "all"
Requires-Dist: mypy-boto3-workspaces-web<1.43.0,>=1.42.0; extra == "all"
Requires-Dist: mypy-boto3-xray<1.43.0,>=1.42.0; extra == "all"
Provides-Extra: essential
Requires-Dist: mypy-boto3-cloudformation<1.43.0,>=1.42.0; extra == "essential"
Requires-Dist: mypy-boto3-dynamodb<1.43.0,>=1.42.0; extra == "essential"
Requires-Dist: mypy-boto3-ec2<1.43.0,>=1.42.0; extra == "essential"
Requires-Dist: mypy-boto3-lambda<1.43.0,>=1.42.0; extra == "essential"
Requires-Dist: mypy-boto3-rds<1.43.0,>=1.42.0; extra == "essential"
Requires-Dist: mypy-boto3-s3<1.43.0,>=1.42.0; extra == "essential"
Requires-Dist: mypy-boto3-sqs<1.43.0,>=1.42.0; extra == "essential"
Provides-Extra: accessanalyzer
Requires-Dist: mypy-boto3-accessanalyzer<1.43.0,>=1.42.0; extra == "accessanalyzer"
Provides-Extra: account
Requires-Dist: mypy-boto3-account<1.43.0,>=1.42.0; extra == "account"
Provides-Extra: acm
Requires-Dist: mypy-boto3-acm<1.43.0,>=1.42.0; extra == "acm"
Provides-Extra: acm-pca
Requires-Dist: mypy-boto3-acm-pca<1.43.0,>=1.42.0; extra == "acm-pca"
Provides-Extra: aiops
Requires-Dist: mypy-boto3-aiops<1.43.0,>=1.42.0; extra == "aiops"
Provides-Extra: amp
Requires-Dist: mypy-boto3-amp<1.43.0,>=1.42.0; extra == "amp"
Provides-Extra: amplify
Requires-Dist: mypy-boto3-amplify<1.43.0,>=1.42.0; extra == "amplify"
Provides-Extra: amplifybackend
Requires-Dist: mypy-boto3-amplifybackend<1.43.0,>=1.42.0; extra == "amplifybackend"
Provides-Extra: amplifyuibuilder
Requires-Dist: mypy-boto3-amplifyuibuilder<1.43.0,>=1.42.0; extra == "amplifyuibuilder"
Provides-Extra: apigateway
Requires-Dist: mypy-boto3-apigateway<1.43.0,>=1.42.0; extra == "apigateway"
Provides-Extra: apigatewaymanagementapi
Requires-Dist: mypy-boto3-apigatewaymanagementapi<1.43.0,>=1.42.0; extra == "apigatewaymanagementapi"
Provides-Extra: apigatewayv2
Requires-Dist: mypy-boto3-apigatewayv2<1.43.0,>=1.42.0; extra == "apigatewayv2"
Provides-Extra: appconfig
Requires-Dist: mypy-boto3-appconfig<1.43.0,>=1.42.0; extra == "appconfig"
Provides-Extra: appconfigdata
Requires-Dist: mypy-boto3-appconfigdata<1.43.0,>=1.42.0; extra == "appconfigdata"
Provides-Extra: appfabric
Requires-Dist: mypy-boto3-appfabric<1.43.0,>=1.42.0; extra == "appfabric"
Provides-Extra: appflow
Requires-Dist: mypy-boto3-appflow<1.43.0,>=1.42.0; extra == "appflow"
Provides-Extra: appintegrations
Requires-Dist: mypy-boto3-appintegrations<1.43.0,>=1.42.0; extra == "appintegrations"
Provides-Extra: application-autoscaling
Requires-Dist: mypy-boto3-application-autoscaling<1.43.0,>=1.42.0; extra == "application-autoscaling"
Provides-Extra: application-insights
Requires-Dist: mypy-boto3-application-insights<1.43.0,>=1.42.0; extra == "application-insights"
Provides-Extra: application-signals
Requires-Dist: mypy-boto3-application-signals<1.43.0,>=1.42.0; extra == "application-signals"
Provides-Extra: applicationcostprofiler
Requires-Dist: mypy-boto3-applicationcostprofiler<1.43.0,>=1.42.0; extra == "applicationcostprofiler"
Provides-Extra: appmesh
Requires-Dist: mypy-boto3-appmesh<1.43.0,>=1.42.0; extra == "appmesh"
Provides-Extra: apprunner
Requires-Dist: mypy-boto3-apprunner<1.43.0,>=1.42.0; extra == "apprunner"
Provides-Extra: appstream
Requires-Dist: mypy-boto3-appstream<1.43.0,>=1.42.0; extra == "appstream"
Provides-Extra: appsync
Requires-Dist: mypy-boto3-appsync<1.43.0,>=1.42.0; extra == "appsync"
Provides-Extra: arc-region-switch
Requires-Dist: mypy-boto3-arc-region-switch<1.43.0,>=1.42.0; extra == "arc-region-switch"
Provides-Extra: arc-zonal-shift
Requires-Dist: mypy-boto3-arc-zonal-shift<1.43.0,>=1.42.0; extra == "arc-zonal-shift"
Provides-Extra: artifact
Requires-Dist: mypy-boto3-artifact<1.43.0,>=1.42.0; extra == "artifact"
Provides-Extra: athena
Requires-Dist: mypy-boto3-athena<1.43.0,>=1.42.0; extra == "athena"
Provides-Extra: auditmanager
Requires-Dist: mypy-boto3-auditmanager<1.43.0,>=1.42.0; extra == "auditmanager"
Provides-Extra: autoscaling
Requires-Dist: mypy-boto3-autoscaling<1.43.0,>=1.42.0; extra == "autoscaling"
Provides-Extra: autoscaling-plans
Requires-Dist: mypy-boto3-autoscaling-plans<1.43.0,>=1.42.0; extra == "autoscaling-plans"
Provides-Extra: b2bi
Requires-Dist: mypy-boto3-b2bi<1.43.0,>=1.42.0; extra == "b2bi"
Provides-Extra: backup
Requires-Dist: mypy-boto3-backup<1.43.0,>=1.42.0; extra == "backup"
Provides-Extra: backup-gateway
Requires-Dist: mypy-boto3-backup-gateway<1.43.0,>=1.42.0; extra == "backup-gateway"
Provides-Extra: backupsearch
Requires-Dist: mypy-boto3-backupsearch<1.43.0,>=1.42.0; extra == "backupsearch"
Provides-Extra: batch
Requires-Dist: mypy-boto3-batch<1.43.0,>=1.42.0; extra == "batch"
Provides-Extra: bcm-dashboards
Requires-Dist: mypy-boto3-bcm-dashboards<1.43.0,>=1.42.0; extra == "bcm-dashboards"
Provides-Extra: bcm-data-exports
Requires-Dist: mypy-boto3-bcm-data-exports<1.43.0,>=1.42.0; extra == "bcm-data-exports"
Provides-Extra: bcm-pricing-calculator
Requires-Dist: mypy-boto3-bcm-pricing-calculator<1.43.0,>=1.42.0; extra == "bcm-pricing-calculator"
Provides-Extra: bcm-recommended-actions
Requires-Dist: mypy-boto3-bcm-recommended-actions<1.43.0,>=1.42.0; extra == "bcm-recommended-actions"
Provides-Extra: bedrock
Requires-Dist: mypy-boto3-bedrock<1.43.0,>=1.42.0; extra == "bedrock"
Provides-Extra: bedrock-agent
Requires-Dist: mypy-boto3-bedrock-agent<1.43.0,>=1.42.0; extra == "bedrock-agent"
Provides-Extra: bedrock-agent-runtime
Requires-Dist: mypy-boto3-bedrock-agent-runtime<1.43.0,>=1.42.0; extra == "bedrock-agent-runtime"
Provides-Extra: bedrock-agentcore
Requires-Dist: mypy-boto3-bedrock-agentcore<1.43.0,>=1.42.0; extra == "bedrock-agentcore"
Provides-Extra: bedrock-agentcore-control
Requires-Dist: mypy-boto3-bedrock-agentcore-control<1.43.0,>=1.42.0; extra == "bedrock-agentcore-control"
Provides-Extra: bedrock-data-automation
Requires-Dist: mypy-boto3-bedrock-data-automation<1.43.0,>=1.42.0; extra == "bedrock-data-automation"
Provides-Extra: bedrock-data-automation-runtime
Requires-Dist: mypy-boto3-bedrock-data-automation-runtime<1.43.0,>=1.42.0; extra == "bedrock-data-automation-runtime"
Provides-Extra: bedrock-runtime
Requires-Dist: mypy-boto3-bedrock-runtime<1.43.0,>=1.42.0; extra == "bedrock-runtime"
Provides-Extra: billing
Requires-Dist: mypy-boto3-billing<1.43.0,>=1.42.0; extra == "billing"
Provides-Extra: billingconductor
Requires-Dist: mypy-boto3-billingconductor<1.43.0,>=1.42.0; extra == "billingconductor"
Provides-Extra: braket
Requires-Dist: mypy-boto3-braket<1.43.0,>=1.42.0; extra == "braket"
Provides-Extra: budgets
Requires-Dist: mypy-boto3-budgets<1.43.0,>=1.42.0; extra == "budgets"
Provides-Extra: ce
Requires-Dist: mypy-boto3-ce<1.43.0,>=1.42.0; extra == "ce"
Provides-Extra: chatbot
Requires-Dist: mypy-boto3-chatbot<1.43.0,>=1.42.0; extra == "chatbot"
Provides-Extra: chime
Requires-Dist: mypy-boto3-chime<1.43.0,>=1.42.0; extra == "chime"
Provides-Extra: chime-sdk-identity
Requires-Dist: mypy-boto3-chime-sdk-identity<1.43.0,>=1.42.0; extra == "chime-sdk-identity"
Provides-Extra: chime-sdk-media-pipelines
Requires-Dist: mypy-boto3-chime-sdk-media-pipelines<1.43.0,>=1.42.0; extra == "chime-sdk-media-pipelines"
Provides-Extra: chime-sdk-meetings
Requires-Dist: mypy-boto3-chime-sdk-meetings<1.43.0,>=1.42.0; extra == "chime-sdk-meetings"
Provides-Extra: chime-sdk-messaging
Requires-Dist: mypy-boto3-chime-sdk-messaging<1.43.0,>=1.42.0; extra == "chime-sdk-messaging"
Provides-Extra: chime-sdk-voice
Requires-Dist: mypy-boto3-chime-sdk-voice<1.43.0,>=1.42.0; extra == "chime-sdk-voice"
Provides-Extra: cleanrooms
Requires-Dist: mypy-boto3-cleanrooms<1.43.0,>=1.42.0; extra == "cleanrooms"
Provides-Extra: cleanroomsml
Requires-Dist: mypy-boto3-cleanroomsml<1.43.0,>=1.42.0; extra == "cleanroomsml"
Provides-Extra: cloud9
Requires-Dist: mypy-boto3-cloud9<1.43.0,>=1.42.0; extra == "cloud9"
Provides-Extra: cloudcontrol
Requires-Dist: mypy-boto3-cloudcontrol<1.43.0,>=1.42.0; extra == "cloudcontrol"
Provides-Extra: clouddirectory
Requires-Dist: mypy-boto3-clouddirectory<1.43.0,>=1.42.0; extra == "clouddirectory"
Provides-Extra: cloudformation
Requires-Dist: mypy-boto3-cloudformation<1.43.0,>=1.42.0; extra == "cloudformation"
Provides-Extra: cloudfront
Requires-Dist: mypy-boto3-cloudfront<1.43.0,>=1.42.0; extra == "cloudfront"
Provides-Extra: cloudfront-keyvaluestore
Requires-Dist: mypy-boto3-cloudfront-keyvaluestore<1.43.0,>=1.42.0; extra == "cloudfront-keyvaluestore"
Provides-Extra: cloudhsm
Requires-Dist: mypy-boto3-cloudhsm<1.43.0,>=1.42.0; extra == "cloudhsm"
Provides-Extra: cloudhsmv2
Requires-Dist: mypy-boto3-cloudhsmv2<1.43.0,>=1.42.0; extra == "cloudhsmv2"
Provides-Extra: cloudsearch
Requires-Dist: mypy-boto3-cloudsearch<1.43.0,>=1.42.0; extra == "cloudsearch"
Provides-Extra: cloudsearchdomain
Requires-Dist: mypy-boto3-cloudsearchdomain<1.43.0,>=1.42.0; extra == "cloudsearchdomain"
Provides-Extra: cloudtrail
Requires-Dist: mypy-boto3-cloudtrail<1.43.0,>=1.42.0; extra == "cloudtrail"
Provides-Extra: cloudtrail-data
Requires-Dist: mypy-boto3-cloudtrail-data<1.43.0,>=1.42.0; extra == "cloudtrail-data"
Provides-Extra: cloudwatch
Requires-Dist: mypy-boto3-cloudwatch<1.43.0,>=1.42.0; extra == "cloudwatch"
Provides-Extra: codeartifact
Requires-Dist: mypy-boto3-codeartifact<1.43.0,>=1.42.0; extra == "codeartifact"
Provides-Extra: codebuild
Requires-Dist: mypy-boto3-codebuild<1.43.0,>=1.42.0; extra == "codebuild"
Provides-Extra: codecatalyst
Requires-Dist: mypy-boto3-codecatalyst<1.43.0,>=1.42.0; extra == "codecatalyst"
Provides-Extra: codecommit
Requires-Dist: mypy-boto3-codecommit<1.43.0,>=1.42.0; extra == "codecommit"
Provides-Extra: codeconnections
Requires-Dist: mypy-boto3-codeconnections<1.43.0,>=1.42.0; extra == "codeconnections"
Provides-Extra: codedeploy
Requires-Dist: mypy-boto3-codedeploy<1.43.0,>=1.42.0; extra == "codedeploy"
Provides-Extra: codeguru-reviewer
Requires-Dist: mypy-boto3-codeguru-reviewer<1.43.0,>=1.42.0; extra == "codeguru-reviewer"
Provides-Extra: codeguru-security
Requires-Dist: mypy-boto3-codeguru-security<1.43.0,>=1.42.0; extra == "codeguru-security"
Provides-Extra: codeguruprofiler
Requires-Dist: mypy-boto3-codeguruprofiler<1.43.0,>=1.42.0; extra == "codeguruprofiler"
Provides-Extra: codepipeline
Requires-Dist: mypy-boto3-codepipeline<1.43.0,>=1.42.0; extra == "codepipeline"
Provides-Extra: codestar-connections
Requires-Dist: mypy-boto3-codestar-connections<1.43.0,>=1.42.0; extra == "codestar-connections"
Provides-Extra: codestar-notifications
Requires-Dist: mypy-boto3-codestar-notifications<1.43.0,>=1.42.0; extra == "codestar-notifications"
Provides-Extra: cognito-identity
Requires-Dist: mypy-boto3-cognito-identity<1.43.0,>=1.42.0; extra == "cognito-identity"
Provides-Extra: cognito-idp
Requires-Dist: mypy-boto3-cognito-idp<1.43.0,>=1.42.0; extra == "cognito-idp"
Provides-Extra: cognito-sync
Requires-Dist: mypy-boto3-cognito-sync<1.43.0,>=1.42.0; extra == "cognito-sync"
Provides-Extra: comprehend
Requires-Dist: mypy-boto3-comprehend<1.43.0,>=1.42.0; extra == "comprehend"
Provides-Extra: comprehendmedical
Requires-Dist: mypy-boto3-comprehendmedical<1.43.0,>=1.42.0; extra == "comprehendmedical"
Provides-Extra: compute-optimizer
Requires-Dist: mypy-boto3-compute-optimizer<1.43.0,>=1.42.0; extra == "compute-optimizer"
Provides-Extra: compute-optimizer-automation
Requires-Dist: mypy-boto3-compute-optimizer-automation<1.43.0,>=1.42.0; extra == "compute-optimizer-automation"
Provides-Extra: config
Requires-Dist: mypy-boto3-config<1.43.0,>=1.42.0; extra == "config"
Provides-Extra: connect
Requires-Dist: mypy-boto3-connect<1.43.0,>=1.42.0; extra == "connect"
Provides-Extra: connect-contact-lens
Requires-Dist: mypy-boto3-connect-contact-lens<1.43.0,>=1.42.0; extra == "connect-contact-lens"
Provides-Extra: connectcampaigns
Requires-Dist: mypy-boto3-connectcampaigns<1.43.0,>=1.42.0; extra == "connectcampaigns"
Provides-Extra: connectcampaignsv2
Requires-Dist: mypy-boto3-connectcampaignsv2<1.43.0,>=1.42.0; extra == "connectcampaignsv2"
Provides-Extra: connectcases
Requires-Dist: mypy-boto3-connectcases<1.43.0,>=1.42.0; extra == "connectcases"
Provides-Extra: connectparticipant
Requires-Dist: mypy-boto3-connectparticipant<1.43.0,>=1.42.0; extra == "connectparticipant"
Provides-Extra: controlcatalog
Requires-Dist: mypy-boto3-controlcatalog<1.43.0,>=1.42.0; extra == "controlcatalog"
Provides-Extra: controltower
Requires-Dist: mypy-boto3-controltower<1.43.0,>=1.42.0; extra == "controltower"
Provides-Extra: cost-optimization-hub
Requires-Dist: mypy-boto3-cost-optimization-hub<1.43.0,>=1.42.0; extra == "cost-optimization-hub"
Provides-Extra: cur
Requires-Dist: mypy-boto3-cur<1.43.0,>=1.42.0; extra == "cur"
Provides-Extra: customer-profiles
Requires-Dist: mypy-boto3-customer-profiles<1.43.0,>=1.42.0; extra == "customer-profiles"
Provides-Extra: databrew
Requires-Dist: mypy-boto3-databrew<1.43.0,>=1.42.0; extra == "databrew"
Provides-Extra: dataexchange
Requires-Dist: mypy-boto3-dataexchange<1.43.0,>=1.42.0; extra == "dataexchange"
Provides-Extra: datapipeline
Requires-Dist: mypy-boto3-datapipeline<1.43.0,>=1.42.0; extra == "datapipeline"
Provides-Extra: datasync
Requires-Dist: mypy-boto3-datasync<1.43.0,>=1.42.0; extra == "datasync"
Provides-Extra: datazone
Requires-Dist: mypy-boto3-datazone<1.43.0,>=1.42.0; extra == "datazone"
Provides-Extra: dax
Requires-Dist: mypy-boto3-dax<1.43.0,>=1.42.0; extra == "dax"
Provides-Extra: deadline
Requires-Dist: mypy-boto3-deadline<1.43.0,>=1.42.0; extra == "deadline"
Provides-Extra: detective
Requires-Dist: mypy-boto3-detective<1.43.0,>=1.42.0; extra == "detective"
Provides-Extra: devicefarm
Requires-Dist: mypy-boto3-devicefarm<1.43.0,>=1.42.0; extra == "devicefarm"
Provides-Extra: devops-guru
Requires-Dist: mypy-boto3-devops-guru<1.43.0,>=1.42.0; extra == "devops-guru"
Provides-Extra: directconnect
Requires-Dist: mypy-boto3-directconnect<1.43.0,>=1.42.0; extra == "directconnect"
Provides-Extra: discovery
Requires-Dist: mypy-boto3-discovery<1.43.0,>=1.42.0; extra == "discovery"
Provides-Extra: dlm
Requires-Dist: mypy-boto3-dlm<1.43.0,>=1.42.0; extra == "dlm"
Provides-Extra: dms
Requires-Dist: mypy-boto3-dms<1.43.0,>=1.42.0; extra == "dms"
Provides-Extra: docdb
Requires-Dist: mypy-boto3-docdb<1.43.0,>=1.42.0; extra == "docdb"
Provides-Extra: docdb-elastic
Requires-Dist: mypy-boto3-docdb-elastic<1.43.0,>=1.42.0; extra == "docdb-elastic"
Provides-Extra: drs
Requires-Dist: mypy-boto3-drs<1.43.0,>=1.42.0; extra == "drs"
Provides-Extra: ds
Requires-Dist: mypy-boto3-ds<1.43.0,>=1.42.0; extra == "ds"
Provides-Extra: ds-data
Requires-Dist: mypy-boto3-ds-data<1.43.0,>=1.42.0; extra == "ds-data"
Provides-Extra: dsql
Requires-Dist: mypy-boto3-dsql<1.43.0,>=1.42.0; extra == "dsql"
Provides-Extra: dynamodb
Requires-Dist: mypy-boto3-dynamodb<1.43.0,>=1.42.0; extra == "dynamodb"
Provides-Extra: dynamodbstreams
Requires-Dist: mypy-boto3-dynamodbstreams<1.43.0,>=1.42.0; extra == "dynamodbstreams"
Provides-Extra: ebs
Requires-Dist: mypy-boto3-ebs<1.43.0,>=1.42.0; extra == "ebs"
Provides-Extra: ec2
Requires-Dist: mypy-boto3-ec2<1.43.0,>=1.42.0; extra == "ec2"
Provides-Extra: ec2-instance-connect
Requires-Dist: mypy-boto3-ec2-instance-connect<1.43.0,>=1.42.0; extra == "ec2-instance-connect"
Provides-Extra: ecr
Requires-Dist: mypy-boto3-ecr<1.43.0,>=1.42.0; extra == "ecr"
Provides-Extra: ecr-public
Requires-Dist: mypy-boto3-ecr-public<1.43.0,>=1.42.0; extra == "ecr-public"
Provides-Extra: ecs
Requires-Dist: mypy-boto3-ecs<1.43.0,>=1.42.0; extra == "ecs"
Provides-Extra: efs
Requires-Dist: mypy-boto3-efs<1.43.0,>=1.42.0; extra == "efs"
Provides-Extra: eks
Requires-Dist: mypy-boto3-eks<1.43.0,>=1.42.0; extra == "eks"
Provides-Extra: eks-auth
Requires-Dist: mypy-boto3-eks-auth<1.43.0,>=1.42.0; extra == "eks-auth"
Provides-Extra: elasticache
Requires-Dist: mypy-boto3-elasticache<1.43.0,>=1.42.0; extra == "elasticache"
Provides-Extra: elasticbeanstalk
Requires-Dist: mypy-boto3-elasticbeanstalk<1.43.0,>=1.42.0; extra == "elasticbeanstalk"
Provides-Extra: elb
Requires-Dist: mypy-boto3-elb<1.43.0,>=1.42.0; extra == "elb"
Provides-Extra: elbv2
Requires-Dist: mypy-boto3-elbv2<1.43.0,>=1.42.0; extra == "elbv2"
Provides-Extra: emr
Requires-Dist: mypy-boto3-emr<1.43.0,>=1.42.0; extra == "emr"
Provides-Extra: emr-containers
Requires-Dist: mypy-boto3-emr-containers<1.43.0,>=1.42.0; extra == "emr-containers"
Provides-Extra: emr-serverless
Requires-Dist: mypy-boto3-emr-serverless<1.43.0,>=1.42.0; extra == "emr-serverless"
Provides-Extra: entityresolution
Requires-Dist: mypy-boto3-entityresolution<1.43.0,>=1.42.0; extra == "entityresolution"
Provides-Extra: es
Requires-Dist: mypy-boto3-es<1.43.0,>=1.42.0; extra == "es"
Provides-Extra: events
Requires-Dist: mypy-boto3-events<1.43.0,>=1.42.0; extra == "events"
Provides-Extra: evidently
Requires-Dist: mypy-boto3-evidently<1.43.0,>=1.42.0; extra == "evidently"
Provides-Extra: evs
Requires-Dist: mypy-boto3-evs<1.43.0,>=1.42.0; extra == "evs"
Provides-Extra: finspace
Requires-Dist: mypy-boto3-finspace<1.43.0,>=1.42.0; extra == "finspace"
Provides-Extra: finspace-data
Requires-Dist: mypy-boto3-finspace-data<1.43.0,>=1.42.0; extra == "finspace-data"
Provides-Extra: firehose
Requires-Dist: mypy-boto3-firehose<1.43.0,>=1.42.0; extra == "firehose"
Provides-Extra: fis
Requires-Dist: mypy-boto3-fis<1.43.0,>=1.42.0; extra == "fis"
Provides-Extra: fms
Requires-Dist: mypy-boto3-fms<1.43.0,>=1.42.0; extra == "fms"
Provides-Extra: forecast
Requires-Dist: mypy-boto3-forecast<1.43.0,>=1.42.0; extra == "forecast"
Provides-Extra: forecastquery
Requires-Dist: mypy-boto3-forecastquery<1.43.0,>=1.42.0; extra == "forecastquery"
Provides-Extra: frauddetector
Requires-Dist: mypy-boto3-frauddetector<1.43.0,>=1.42.0; extra == "frauddetector"
Provides-Extra: freetier
Requires-Dist: mypy-boto3-freetier<1.43.0,>=1.42.0; extra == "freetier"
Provides-Extra: fsx
Requires-Dist: mypy-boto3-fsx<1.43.0,>=1.42.0; extra == "fsx"
Provides-Extra: gamelift
Requires-Dist: mypy-boto3-gamelift<1.43.0,>=1.42.0; extra == "gamelift"
Provides-Extra: gameliftstreams
Requires-Dist: mypy-boto3-gameliftstreams<1.43.0,>=1.42.0; extra == "gameliftstreams"
Provides-Extra: geo-maps
Requires-Dist: mypy-boto3-geo-maps<1.43.0,>=1.42.0; extra == "geo-maps"
Provides-Extra: geo-places
Requires-Dist: mypy-boto3-geo-places<1.43.0,>=1.42.0; extra == "geo-places"
Provides-Extra: geo-routes
Requires-Dist: mypy-boto3-geo-routes<1.43.0,>=1.42.0; extra == "geo-routes"
Provides-Extra: glacier
Requires-Dist: mypy-boto3-glacier<1.43.0,>=1.42.0; extra == "glacier"
Provides-Extra: globalaccelerator
Requires-Dist: mypy-boto3-globalaccelerator<1.43.0,>=1.42.0; extra == "globalaccelerator"
Provides-Extra: glue
Requires-Dist: mypy-boto3-glue<1.43.0,>=1.42.0; extra == "glue"
Provides-Extra: grafana
Requires-Dist: mypy-boto3-grafana<1.43.0,>=1.42.0; extra == "grafana"
Provides-Extra: greengrass
Requires-Dist: mypy-boto3-greengrass<1.43.0,>=1.42.0; extra == "greengrass"
Provides-Extra: greengrassv2
Requires-Dist: mypy-boto3-greengrassv2<1.43.0,>=1.42.0; extra == "greengrassv2"
Provides-Extra: groundstation
Requires-Dist: mypy-boto3-groundstation<1.43.0,>=1.42.0; extra == "groundstation"
Provides-Extra: guardduty
Requires-Dist: mypy-boto3-guardduty<1.43.0,>=1.42.0; extra == "guardduty"
Provides-Extra: health
Requires-Dist: mypy-boto3-health<1.43.0,>=1.42.0; extra == "health"
Provides-Extra: healthlake
Requires-Dist: mypy-boto3-healthlake<1.43.0,>=1.42.0; extra == "healthlake"
Provides-Extra: iam
Requires-Dist: mypy-boto3-iam<1.43.0,>=1.42.0; extra == "iam"
Provides-Extra: identitystore
Requires-Dist: mypy-boto3-identitystore<1.43.0,>=1.42.0; extra == "identitystore"
Provides-Extra: imagebuilder
Requires-Dist: mypy-boto3-imagebuilder<1.43.0,>=1.42.0; extra == "imagebuilder"
Provides-Extra: importexport
Requires-Dist: mypy-boto3-importexport<1.43.0,>=1.42.0; extra == "importexport"
Provides-Extra: inspector
Requires-Dist: mypy-boto3-inspector<1.43.0,>=1.42.0; extra == "inspector"
Provides-Extra: inspector-scan
Requires-Dist: mypy-boto3-inspector-scan<1.43.0,>=1.42.0; extra == "inspector-scan"
Provides-Extra: inspector2
Requires-Dist: mypy-boto3-inspector2<1.43.0,>=1.42.0; extra == "inspector2"
Provides-Extra: internetmonitor
Requires-Dist: mypy-boto3-internetmonitor<1.43.0,>=1.42.0; extra == "internetmonitor"
Provides-Extra: invoicing
Requires-Dist: mypy-boto3-invoicing<1.43.0,>=1.42.0; extra == "invoicing"
Provides-Extra: iot
Requires-Dist: mypy-boto3-iot<1.43.0,>=1.42.0; extra == "iot"
Provides-Extra: iot-data
Requires-Dist: mypy-boto3-iot-data<1.43.0,>=1.42.0; extra == "iot-data"
Provides-Extra: iot-jobs-data
Requires-Dist: mypy-boto3-iot-jobs-data<1.43.0,>=1.42.0; extra == "iot-jobs-data"
Provides-Extra: iot-managed-integrations
Requires-Dist: mypy-boto3-iot-managed-integrations<1.43.0,>=1.42.0; extra == "iot-managed-integrations"
Provides-Extra: iotanalytics
Requires-Dist: mypy-boto3-iotanalytics<1.43.0,>=1.42.0; extra == "iotanalytics"
Provides-Extra: iotdeviceadvisor
Requires-Dist: mypy-boto3-iotdeviceadvisor<1.43.0,>=1.42.0; extra == "iotdeviceadvisor"
Provides-Extra: iotevents
Requires-Dist: mypy-boto3-iotevents<1.43.0,>=1.42.0; extra == "iotevents"
Provides-Extra: iotevents-data
Requires-Dist: mypy-boto3-iotevents-data<1.43.0,>=1.42.0; extra == "iotevents-data"
Provides-Extra: iotfleetwise
Requires-Dist: mypy-boto3-iotfleetwise<1.43.0,>=1.42.0; extra == "iotfleetwise"
Provides-Extra: iotsecuretunneling
Requires-Dist: mypy-boto3-iotsecuretunneling<1.43.0,>=1.42.0; extra == "iotsecuretunneling"
Provides-Extra: iotsitewise
Requires-Dist: mypy-boto3-iotsitewise<1.43.0,>=1.42.0; extra == "iotsitewise"
Provides-Extra: iotthingsgraph
Requires-Dist: mypy-boto3-iotthingsgraph<1.43.0,>=1.42.0; extra == "iotthingsgraph"
Provides-Extra: iottwinmaker
Requires-Dist: mypy-boto3-iottwinmaker<1.43.0,>=1.42.0; extra == "iottwinmaker"
Provides-Extra: iotwireless
Requires-Dist: mypy-boto3-iotwireless<1.43.0,>=1.42.0; extra == "iotwireless"
Provides-Extra: ivs
Requires-Dist: mypy-boto3-ivs<1.43.0,>=1.42.0; extra == "ivs"
Provides-Extra: ivs-realtime
Requires-Dist: mypy-boto3-ivs-realtime<1.43.0,>=1.42.0; extra == "ivs-realtime"
Provides-Extra: ivschat
Requires-Dist: mypy-boto3-ivschat<1.43.0,>=1.42.0; extra == "ivschat"
Provides-Extra: kafka
Requires-Dist: mypy-boto3-kafka<1.43.0,>=1.42.0; extra == "kafka"
Provides-Extra: kafkaconnect
Requires-Dist: mypy-boto3-kafkaconnect<1.43.0,>=1.42.0; extra == "kafkaconnect"
Provides-Extra: kendra
Requires-Dist: mypy-boto3-kendra<1.43.0,>=1.42.0; extra == "kendra"
Provides-Extra: kendra-ranking
Requires-Dist: mypy-boto3-kendra-ranking<1.43.0,>=1.42.0; extra == "kendra-ranking"
Provides-Extra: keyspaces
Requires-Dist: mypy-boto3-keyspaces<1.43.0,>=1.42.0; extra == "keyspaces"
Provides-Extra: keyspacesstreams
Requires-Dist: mypy-boto3-keyspacesstreams<1.43.0,>=1.42.0; extra == "keyspacesstreams"
Provides-Extra: kinesis
Requires-Dist: mypy-boto3-kinesis<1.43.0,>=1.42.0; extra == "kinesis"
Provides-Extra: kinesis-video-archived-media
Requires-Dist: mypy-boto3-kinesis-video-archived-media<1.43.0,>=1.42.0; extra == "kinesis-video-archived-media"
Provides-Extra: kinesis-video-media
Requires-Dist: mypy-boto3-kinesis-video-media<1.43.0,>=1.42.0; extra == "kinesis-video-media"
Provides-Extra: kinesis-video-signaling
Requires-Dist: mypy-boto3-kinesis-video-signaling<1.43.0,>=1.42.0; extra == "kinesis-video-signaling"
Provides-Extra: kinesis-video-webrtc-storage
Requires-Dist: mypy-boto3-kinesis-video-webrtc-storage<1.43.0,>=1.42.0; extra == "kinesis-video-webrtc-storage"
Provides-Extra: kinesisanalytics
Requires-Dist: mypy-boto3-kinesisanalytics<1.43.0,>=1.42.0; extra == "kinesisanalytics"
Provides-Extra: kinesisanalyticsv2
Requires-Dist: mypy-boto3-kinesisanalyticsv2<1.43.0,>=1.42.0; extra == "kinesisanalyticsv2"
Provides-Extra: kinesisvideo
Requires-Dist: mypy-boto3-kinesisvideo<1.43.0,>=1.42.0; extra == "kinesisvideo"
Provides-Extra: kms
Requires-Dist: mypy-boto3-kms<1.43.0,>=1.42.0; extra == "kms"
Provides-Extra: lakeformation
Requires-Dist: mypy-boto3-lakeformation<1.43.0,>=1.42.0; extra == "lakeformation"
Provides-Extra: lambda
Requires-Dist: mypy-boto3-lambda<1.43.0,>=1.42.0; extra == "lambda"
Provides-Extra: launch-wizard
Requires-Dist: mypy-boto3-launch-wizard<1.43.0,>=1.42.0; extra == "launch-wizard"
Provides-Extra: lex-models
Requires-Dist: mypy-boto3-lex-models<1.43.0,>=1.42.0; extra == "lex-models"
Provides-Extra: lex-runtime
Requires-Dist: mypy-boto3-lex-runtime<1.43.0,>=1.42.0; extra == "lex-runtime"
Provides-Extra: lexv2-models
Requires-Dist: mypy-boto3-lexv2-models<1.43.0,>=1.42.0; extra == "lexv2-models"
Provides-Extra: lexv2-runtime
Requires-Dist: mypy-boto3-lexv2-runtime<1.43.0,>=1.42.0; extra == "lexv2-runtime"
Provides-Extra: license-manager
Requires-Dist: mypy-boto3-license-manager<1.43.0,>=1.42.0; extra == "license-manager"
Provides-Extra: license-manager-linux-subscriptions
Requires-Dist: mypy-boto3-license-manager-linux-subscriptions<1.43.0,>=1.42.0; extra == "license-manager-linux-subscriptions"
Provides-Extra: license-manager-user-subscriptions
Requires-Dist: mypy-boto3-license-manager-user-subscriptions<1.43.0,>=1.42.0; extra == "license-manager-user-subscriptions"
Provides-Extra: lightsail
Requires-Dist: mypy-boto3-lightsail<1.43.0,>=1.42.0; extra == "lightsail"
Provides-Extra: location
Requires-Dist: mypy-boto3-location<1.43.0,>=1.42.0; extra == "location"
Provides-Extra: logs
Requires-Dist: mypy-boto3-logs<1.43.0,>=1.42.0; extra == "logs"
Provides-Extra: lookoutequipment
Requires-Dist: mypy-boto3-lookoutequipment<1.43.0,>=1.42.0; extra == "lookoutequipment"
Provides-Extra: m2
Requires-Dist: mypy-boto3-m2<1.43.0,>=1.42.0; extra == "m2"
Provides-Extra: machinelearning
Requires-Dist: mypy-boto3-machinelearning<1.43.0,>=1.42.0; extra == "machinelearning"
Provides-Extra: macie2
Requires-Dist: mypy-boto3-macie2<1.43.0,>=1.42.0; extra == "macie2"
Provides-Extra: mailmanager
Requires-Dist: mypy-boto3-mailmanager<1.43.0,>=1.42.0; extra == "mailmanager"
Provides-Extra: managedblockchain
Requires-Dist: mypy-boto3-managedblockchain<1.43.0,>=1.42.0; extra == "managedblockchain"
Provides-Extra: managedblockchain-query
Requires-Dist: mypy-boto3-managedblockchain-query<1.43.0,>=1.42.0; extra == "managedblockchain-query"
Provides-Extra: marketplace-agreement
Requires-Dist: mypy-boto3-marketplace-agreement<1.43.0,>=1.42.0; extra == "marketplace-agreement"
Provides-Extra: marketplace-catalog
Requires-Dist: mypy-boto3-marketplace-catalog<1.43.0,>=1.42.0; extra == "marketplace-catalog"
Provides-Extra: marketplace-deployment
Requires-Dist: mypy-boto3-marketplace-deployment<1.43.0,>=1.42.0; extra == "marketplace-deployment"
Provides-Extra: marketplace-entitlement
Requires-Dist: mypy-boto3-marketplace-entitlement<1.43.0,>=1.42.0; extra == "marketplace-entitlement"
Provides-Extra: marketplace-reporting
Requires-Dist: mypy-boto3-marketplace-reporting<1.43.0,>=1.42.0; extra == "marketplace-reporting"
Provides-Extra: marketplacecommerceanalytics
Requires-Dist: mypy-boto3-marketplacecommerceanalytics<1.43.0,>=1.42.0; extra == "marketplacecommerceanalytics"
Provides-Extra: mediaconnect
Requires-Dist: mypy-boto3-mediaconnect<1.43.0,>=1.42.0; extra == "mediaconnect"
Provides-Extra: mediaconvert
Requires-Dist: mypy-boto3-mediaconvert<1.43.0,>=1.42.0; extra == "mediaconvert"
Provides-Extra: medialive
Requires-Dist: mypy-boto3-medialive<1.43.0,>=1.42.0; extra == "medialive"
Provides-Extra: mediapackage
Requires-Dist: mypy-boto3-mediapackage<1.43.0,>=1.42.0; extra == "mediapackage"
Provides-Extra: mediapackage-vod
Requires-Dist: mypy-boto3-mediapackage-vod<1.43.0,>=1.42.0; extra == "mediapackage-vod"
Provides-Extra: mediapackagev2
Requires-Dist: mypy-boto3-mediapackagev2<1.43.0,>=1.42.0; extra == "mediapackagev2"
Provides-Extra: mediastore
Requires-Dist: mypy-boto3-mediastore<1.43.0,>=1.42.0; extra == "mediastore"
Provides-Extra: mediastore-data
Requires-Dist: mypy-boto3-mediastore-data<1.43.0,>=1.42.0; extra == "mediastore-data"
Provides-Extra: mediatailor
Requires-Dist: mypy-boto3-mediatailor<1.43.0,>=1.42.0; extra == "mediatailor"
Provides-Extra: medical-imaging
Requires-Dist: mypy-boto3-medical-imaging<1.43.0,>=1.42.0; extra == "medical-imaging"
Provides-Extra: memorydb
Requires-Dist: mypy-boto3-memorydb<1.43.0,>=1.42.0; extra == "memorydb"
Provides-Extra: meteringmarketplace
Requires-Dist: mypy-boto3-meteringmarketplace<1.43.0,>=1.42.0; extra == "meteringmarketplace"
Provides-Extra: mgh
Requires-Dist: mypy-boto3-mgh<1.43.0,>=1.42.0; extra == "mgh"
Provides-Extra: mgn
Requires-Dist: mypy-boto3-mgn<1.43.0,>=1.42.0; extra == "mgn"
Provides-Extra: migration-hub-refactor-spaces
Requires-Dist: mypy-boto3-migration-hub-refactor-spaces<1.43.0,>=1.42.0; extra == "migration-hub-refactor-spaces"
Provides-Extra: migrationhub-config
Requires-Dist: mypy-boto3-migrationhub-config<1.43.0,>=1.42.0; extra == "migrationhub-config"
Provides-Extra: migrationhuborchestrator
Requires-Dist: mypy-boto3-migrationhuborchestrator<1.43.0,>=1.42.0; extra == "migrationhuborchestrator"
Provides-Extra: migrationhubstrategy
Requires-Dist: mypy-boto3-migrationhubstrategy<1.43.0,>=1.42.0; extra == "migrationhubstrategy"
Provides-Extra: mpa
Requires-Dist: mypy-boto3-mpa<1.43.0,>=1.42.0; extra == "mpa"
Provides-Extra: mq
Requires-Dist: mypy-boto3-mq<1.43.0,>=1.42.0; extra == "mq"
Provides-Extra: mturk
Requires-Dist: mypy-boto3-mturk<1.43.0,>=1.42.0; extra == "mturk"
Provides-Extra: mwaa
Requires-Dist: mypy-boto3-mwaa<1.43.0,>=1.42.0; extra == "mwaa"
Provides-Extra: mwaa-serverless
Requires-Dist: mypy-boto3-mwaa-serverless<1.43.0,>=1.42.0; extra == "mwaa-serverless"
Provides-Extra: neptune
Requires-Dist: mypy-boto3-neptune<1.43.0,>=1.42.0; extra == "neptune"
Provides-Extra: neptune-graph
Requires-Dist: mypy-boto3-neptune-graph<1.43.0,>=1.42.0; extra == "neptune-graph"
Provides-Extra: neptunedata
Requires-Dist: mypy-boto3-neptunedata<1.43.0,>=1.42.0; extra == "neptunedata"
Provides-Extra: network-firewall
Requires-Dist: mypy-boto3-network-firewall<1.43.0,>=1.42.0; extra == "network-firewall"
Provides-Extra: networkflowmonitor
Requires-Dist: mypy-boto3-networkflowmonitor<1.43.0,>=1.42.0; extra == "networkflowmonitor"
Provides-Extra: networkmanager
Requires-Dist: mypy-boto3-networkmanager<1.43.0,>=1.42.0; extra == "networkmanager"
Provides-Extra: networkmonitor
Requires-Dist: mypy-boto3-networkmonitor<1.43.0,>=1.42.0; extra == "networkmonitor"
Provides-Extra: notifications
Requires-Dist: mypy-boto3-notifications<1.43.0,>=1.42.0; extra == "notifications"
Provides-Extra: notificationscontacts
Requires-Dist: mypy-boto3-notificationscontacts<1.43.0,>=1.42.0; extra == "notificationscontacts"
Provides-Extra: nova-act
Requires-Dist: mypy-boto3-nova-act<1.43.0,>=1.42.0; extra == "nova-act"
Provides-Extra: oam
Requires-Dist: mypy-boto3-oam<1.43.0,>=1.42.0; extra == "oam"
Provides-Extra: observabilityadmin
Requires-Dist: mypy-boto3-observabilityadmin<1.43.0,>=1.42.0; extra == "observabilityadmin"
Provides-Extra: odb
Requires-Dist: mypy-boto3-odb<1.43.0,>=1.42.0; extra == "odb"
Provides-Extra: omics
Requires-Dist: mypy-boto3-omics<1.43.0,>=1.42.0; extra == "omics"
Provides-Extra: opensearch
Requires-Dist: mypy-boto3-opensearch<1.43.0,>=1.42.0; extra == "opensearch"
Provides-Extra: opensearchserverless
Requires-Dist: mypy-boto3-opensearchserverless<1.43.0,>=1.42.0; extra == "opensearchserverless"
Provides-Extra: organizations
Requires-Dist: mypy-boto3-organizations<1.43.0,>=1.42.0; extra == "organizations"
Provides-Extra: osis
Requires-Dist: mypy-boto3-osis<1.43.0,>=1.42.0; extra == "osis"
Provides-Extra: outposts
Requires-Dist: mypy-boto3-outposts<1.43.0,>=1.42.0; extra == "outposts"
Provides-Extra: panorama
Requires-Dist: mypy-boto3-panorama<1.43.0,>=1.42.0; extra == "panorama"
Provides-Extra: partnercentral-account
Requires-Dist: mypy-boto3-partnercentral-account<1.43.0,>=1.42.0; extra == "partnercentral-account"
Provides-Extra: partnercentral-benefits
Requires-Dist: mypy-boto3-partnercentral-benefits<1.43.0,>=1.42.0; extra == "partnercentral-benefits"
Provides-Extra: partnercentral-channel
Requires-Dist: mypy-boto3-partnercentral-channel<1.43.0,>=1.42.0; extra == "partnercentral-channel"
Provides-Extra: partnercentral-selling
Requires-Dist: mypy-boto3-partnercentral-selling<1.43.0,>=1.42.0; extra == "partnercentral-selling"
Provides-Extra: payment-cryptography
Requires-Dist: mypy-boto3-payment-cryptography<1.43.0,>=1.42.0; extra == "payment-cryptography"
Provides-Extra: payment-cryptography-data
Requires-Dist: mypy-boto3-payment-cryptography-data<1.43.0,>=1.42.0; extra == "payment-cryptography-data"
Provides-Extra: pca-connector-ad
Requires-Dist: mypy-boto3-pca-connector-ad<1.43.0,>=1.42.0; extra == "pca-connector-ad"
Provides-Extra: pca-connector-scep
Requires-Dist: mypy-boto3-pca-connector-scep<1.43.0,>=1.42.0; extra == "pca-connector-scep"
Provides-Extra: pcs
Requires-Dist: mypy-boto3-pcs<1.43.0,>=1.42.0; extra == "pcs"
Provides-Extra: personalize
Requires-Dist: mypy-boto3-personalize<1.43.0,>=1.42.0; extra == "personalize"
Provides-Extra: personalize-events
Requires-Dist: mypy-boto3-personalize-events<1.43.0,>=1.42.0; extra == "personalize-events"
Provides-Extra: personalize-runtime
Requires-Dist: mypy-boto3-personalize-runtime<1.43.0,>=1.42.0; extra == "personalize-runtime"
Provides-Extra: pi
Requires-Dist: mypy-boto3-pi<1.43.0,>=1.42.0; extra == "pi"
Provides-Extra: pinpoint
Requires-Dist: mypy-boto3-pinpoint<1.43.0,>=1.42.0; extra == "pinpoint"
Provides-Extra: pinpoint-email
Requires-Dist: mypy-boto3-pinpoint-email<1.43.0,>=1.42.0; extra == "pinpoint-email"
Provides-Extra: pinpoint-sms-voice
Requires-Dist: mypy-boto3-pinpoint-sms-voice<1.43.0,>=1.42.0; extra == "pinpoint-sms-voice"
Provides-Extra: pinpoint-sms-voice-v2
Requires-Dist: mypy-boto3-pinpoint-sms-voice-v2<1.43.0,>=1.42.0; extra == "pinpoint-sms-voice-v2"
Provides-Extra: pipes
Requires-Dist: mypy-boto3-pipes<1.43.0,>=1.42.0; extra == "pipes"
Provides-Extra: polly
Requires-Dist: mypy-boto3-polly<1.43.0,>=1.42.0; extra == "polly"
Provides-Extra: pricing
Requires-Dist: mypy-boto3-pricing<1.43.0,>=1.42.0; extra == "pricing"
Provides-Extra: proton
Requires-Dist: mypy-boto3-proton<1.43.0,>=1.42.0; extra == "proton"
Provides-Extra: qapps
Requires-Dist: mypy-boto3-qapps<1.43.0,>=1.42.0; extra == "qapps"
Provides-Extra: qbusiness
Requires-Dist: mypy-boto3-qbusiness<1.43.0,>=1.42.0; extra == "qbusiness"
Provides-Extra: qconnect
Requires-Dist: mypy-boto3-qconnect<1.43.0,>=1.42.0; extra == "qconnect"
Provides-Extra: quicksight
Requires-Dist: mypy-boto3-quicksight<1.43.0,>=1.42.0; extra == "quicksight"
Provides-Extra: ram
Requires-Dist: mypy-boto3-ram<1.43.0,>=1.42.0; extra == "ram"
Provides-Extra: rbin
Requires-Dist: mypy-boto3-rbin<1.43.0,>=1.42.0; extra == "rbin"
Provides-Extra: rds
Requires-Dist: mypy-boto3-rds<1.43.0,>=1.42.0; extra == "rds"
Provides-Extra: rds-data
Requires-Dist: mypy-boto3-rds-data<1.43.0,>=1.42.0; extra == "rds-data"
Provides-Extra: redshift
Requires-Dist: mypy-boto3-redshift<1.43.0,>=1.42.0; extra == "redshift"
Provides-Extra: redshift-data
Requires-Dist: mypy-boto3-redshift-data<1.43.0,>=1.42.0; extra == "redshift-data"
Provides-Extra: redshift-serverless
Requires-Dist: mypy-boto3-redshift-serverless<1.43.0,>=1.42.0; extra == "redshift-serverless"
Provides-Extra: rekognition
Requires-Dist: mypy-boto3-rekognition<1.43.0,>=1.42.0; extra == "rekognition"
Provides-Extra: repostspace
Requires-Dist: mypy-boto3-repostspace<1.43.0,>=1.42.0; extra == "repostspace"
Provides-Extra: resiliencehub
Requires-Dist: mypy-boto3-resiliencehub<1.43.0,>=1.42.0; extra == "resiliencehub"
Provides-Extra: resource-explorer-2
Requires-Dist: mypy-boto3-resource-explorer-2<1.43.0,>=1.42.0; extra == "resource-explorer-2"
Provides-Extra: resource-groups
Requires-Dist: mypy-boto3-resource-groups<1.43.0,>=1.42.0; extra == "resource-groups"
Provides-Extra: resourcegroupstaggingapi
Requires-Dist: mypy-boto3-resourcegroupstaggingapi<1.43.0,>=1.42.0; extra == "resourcegroupstaggingapi"
Provides-Extra: rolesanywhere
Requires-Dist: mypy-boto3-rolesanywhere<1.43.0,>=1.42.0; extra == "rolesanywhere"
Provides-Extra: route53
Requires-Dist: mypy-boto3-route53<1.43.0,>=1.42.0; extra == "route53"
Provides-Extra: route53-recovery-cluster
Requires-Dist: mypy-boto3-route53-recovery-cluster<1.43.0,>=1.42.0; extra == "route53-recovery-cluster"
Provides-Extra: route53-recovery-control-config
Requires-Dist: mypy-boto3-route53-recovery-control-config<1.43.0,>=1.42.0; extra == "route53-recovery-control-config"
Provides-Extra: route53-recovery-readiness
Requires-Dist: mypy-boto3-route53-recovery-readiness<1.43.0,>=1.42.0; extra == "route53-recovery-readiness"
Provides-Extra: route53domains
Requires-Dist: mypy-boto3-route53domains<1.43.0,>=1.42.0; extra == "route53domains"
Provides-Extra: route53globalresolver
Requires-Dist: mypy-boto3-route53globalresolver<1.43.0,>=1.42.0; extra == "route53globalresolver"
Provides-Extra: route53profiles
Requires-Dist: mypy-boto3-route53profiles<1.43.0,>=1.42.0; extra == "route53profiles"
Provides-Extra: route53resolver
Requires-Dist: mypy-boto3-route53resolver<1.43.0,>=1.42.0; extra == "route53resolver"
Provides-Extra: rtbfabric
Requires-Dist: mypy-boto3-rtbfabric<1.43.0,>=1.42.0; extra == "rtbfabric"
Provides-Extra: rum
Requires-Dist: mypy-boto3-rum<1.43.0,>=1.42.0; extra == "rum"
Provides-Extra: s3
Requires-Dist: mypy-boto3-s3<1.43.0,>=1.42.0; extra == "s3"
Provides-Extra: s3control
Requires-Dist: mypy-boto3-s3control<1.43.0,>=1.42.0; extra == "s3control"
Provides-Extra: s3outposts
Requires-Dist: mypy-boto3-s3outposts<1.43.0,>=1.42.0; extra == "s3outposts"
Provides-Extra: s3tables
Requires-Dist: mypy-boto3-s3tables<1.43.0,>=1.42.0; extra == "s3tables"
Provides-Extra: s3vectors
Requires-Dist: mypy-boto3-s3vectors<1.43.0,>=1.42.0; extra == "s3vectors"
Provides-Extra: sagemaker
Requires-Dist: mypy-boto3-sagemaker<1.43.0,>=1.42.0; extra == "sagemaker"
Provides-Extra: sagemaker-a2i-runtime
Requires-Dist: mypy-boto3-sagemaker-a2i-runtime<1.43.0,>=1.42.0; extra == "sagemaker-a2i-runtime"
Provides-Extra: sagemaker-edge
Requires-Dist: mypy-boto3-sagemaker-edge<1.43.0,>=1.42.0; extra == "sagemaker-edge"
Provides-Extra: sagemaker-featurestore-runtime
Requires-Dist: mypy-boto3-sagemaker-featurestore-runtime<1.43.0,>=1.42.0; extra == "sagemaker-featurestore-runtime"
Provides-Extra: sagemaker-geospatial
Requires-Dist: mypy-boto3-sagemaker-geospatial<1.43.0,>=1.42.0; extra == "sagemaker-geospatial"
Provides-Extra: sagemaker-metrics
Requires-Dist: mypy-boto3-sagemaker-metrics<1.43.0,>=1.42.0; extra == "sagemaker-metrics"
Provides-Extra: sagemaker-runtime
Requires-Dist: mypy-boto3-sagemaker-runtime<1.43.0,>=1.42.0; extra == "sagemaker-runtime"
Provides-Extra: savingsplans
Requires-Dist: mypy-boto3-savingsplans<1.43.0,>=1.42.0; extra == "savingsplans"
Provides-Extra: scheduler
Requires-Dist: mypy-boto3-scheduler<1.43.0,>=1.42.0; extra == "scheduler"
Provides-Extra: schemas
Requires-Dist: mypy-boto3-schemas<1.43.0,>=1.42.0; extra == "schemas"
Provides-Extra: sdb
Requires-Dist: mypy-boto3-sdb<1.43.0,>=1.42.0; extra == "sdb"
Provides-Extra: secretsmanager
Requires-Dist: mypy-boto3-secretsmanager<1.43.0,>=1.42.0; extra == "secretsmanager"
Provides-Extra: security-ir
Requires-Dist: mypy-boto3-security-ir<1.43.0,>=1.42.0; extra == "security-ir"
Provides-Extra: securityhub
Requires-Dist: mypy-boto3-securityhub<1.43.0,>=1.42.0; extra == "securityhub"
Provides-Extra: securitylake
Requires-Dist: mypy-boto3-securitylake<1.43.0,>=1.42.0; extra == "securitylake"
Provides-Extra: serverlessrepo
Requires-Dist: mypy-boto3-serverlessrepo<1.43.0,>=1.42.0; extra == "serverlessrepo"
Provides-Extra: service-quotas
Requires-Dist: mypy-boto3-service-quotas<1.43.0,>=1.42.0; extra == "service-quotas"
Provides-Extra: servicecatalog
Requires-Dist: mypy-boto3-servicecatalog<1.43.0,>=1.42.0; extra == "servicecatalog"
Provides-Extra: servicecatalog-appregistry
Requires-Dist: mypy-boto3-servicecatalog-appregistry<1.43.0,>=1.42.0; extra == "servicecatalog-appregistry"
Provides-Extra: servicediscovery
Requires-Dist: mypy-boto3-servicediscovery<1.43.0,>=1.42.0; extra == "servicediscovery"
Provides-Extra: ses
Requires-Dist: mypy-boto3-ses<1.43.0,>=1.42.0; extra == "ses"
Provides-Extra: sesv2
Requires-Dist: mypy-boto3-sesv2<1.43.0,>=1.42.0; extra == "sesv2"
Provides-Extra: shield
Requires-Dist: mypy-boto3-shield<1.43.0,>=1.42.0; extra == "shield"
Provides-Extra: signer
Requires-Dist: mypy-boto3-signer<1.43.0,>=1.42.0; extra == "signer"
Provides-Extra: signin
Requires-Dist: mypy-boto3-signin<1.43.0,>=1.42.0; extra == "signin"
Provides-Extra: simspaceweaver
Requires-Dist: mypy-boto3-simspaceweaver<1.43.0,>=1.42.0; extra == "simspaceweaver"
Provides-Extra: snow-device-management
Requires-Dist: mypy-boto3-snow-device-management<1.43.0,>=1.42.0; extra == "snow-device-management"
Provides-Extra: snowball
Requires-Dist: mypy-boto3-snowball<1.43.0,>=1.42.0; extra == "snowball"
Provides-Extra: sns
Requires-Dist: mypy-boto3-sns<1.43.0,>=1.42.0; extra == "sns"
Provides-Extra: socialmessaging
Requires-Dist: mypy-boto3-socialmessaging<1.43.0,>=1.42.0; extra == "socialmessaging"
Provides-Extra: sqs
Requires-Dist: mypy-boto3-sqs<1.43.0,>=1.42.0; extra == "sqs"
Provides-Extra: ssm
Requires-Dist: mypy-boto3-ssm<1.43.0,>=1.42.0; extra == "ssm"
Provides-Extra: ssm-contacts
Requires-Dist: mypy-boto3-ssm-contacts<1.43.0,>=1.42.0; extra == "ssm-contacts"
Provides-Extra: ssm-guiconnect
Requires-Dist: mypy-boto3-ssm-guiconnect<1.43.0,>=1.42.0; extra == "ssm-guiconnect"
Provides-Extra: ssm-incidents
Requires-Dist: mypy-boto3-ssm-incidents<1.43.0,>=1.42.0; extra == "ssm-incidents"
Provides-Extra: ssm-quicksetup
Requires-Dist: mypy-boto3-ssm-quicksetup<1.43.0,>=1.42.0; extra == "ssm-quicksetup"
Provides-Extra: ssm-sap
Requires-Dist: mypy-boto3-ssm-sap<1.43.0,>=1.42.0; extra == "ssm-sap"
Provides-Extra: sso
Requires-Dist: mypy-boto3-sso<1.43.0,>=1.42.0; extra == "sso"
Provides-Extra: sso-admin
Requires-Dist: mypy-boto3-sso-admin<1.43.0,>=1.42.0; extra == "sso-admin"
Provides-Extra: sso-oidc
Requires-Dist: mypy-boto3-sso-oidc<1.43.0,>=1.42.0; extra == "sso-oidc"
Provides-Extra: stepfunctions
Requires-Dist: mypy-boto3-stepfunctions<1.43.0,>=1.42.0; extra == "stepfunctions"
Provides-Extra: storagegateway
Requires-Dist: mypy-boto3-storagegateway<1.43.0,>=1.42.0; extra == "storagegateway"
Provides-Extra: sts
Requires-Dist: mypy-boto3-sts<1.43.0,>=1.42.0; extra == "sts"
Provides-Extra: supplychain
Requires-Dist: mypy-boto3-supplychain<1.43.0,>=1.42.0; extra == "supplychain"
Provides-Extra: support
Requires-Dist: mypy-boto3-support<1.43.0,>=1.42.0; extra == "support"
Provides-Extra: support-app
Requires-Dist: mypy-boto3-support-app<1.43.0,>=1.42.0; extra == "support-app"
Provides-Extra: swf
Requires-Dist: mypy-boto3-swf<1.43.0,>=1.42.0; extra == "swf"
Provides-Extra: synthetics
Requires-Dist: mypy-boto3-synthetics<1.43.0,>=1.42.0; extra == "synthetics"
Provides-Extra: taxsettings
Requires-Dist: mypy-boto3-taxsettings<1.43.0,>=1.42.0; extra == "taxsettings"
Provides-Extra: textract
Requires-Dist: mypy-boto3-textract<1.43.0,>=1.42.0; extra == "textract"
Provides-Extra: timestream-influxdb
Requires-Dist: mypy-boto3-timestream-influxdb<1.43.0,>=1.42.0; extra == "timestream-influxdb"
Provides-Extra: timestream-query
Requires-Dist: mypy-boto3-timestream-query<1.43.0,>=1.42.0; extra == "timestream-query"
Provides-Extra: timestream-write
Requires-Dist: mypy-boto3-timestream-write<1.43.0,>=1.42.0; extra == "timestream-write"
Provides-Extra: tnb
Requires-Dist: mypy-boto3-tnb<1.43.0,>=1.42.0; extra == "tnb"
Provides-Extra: transcribe
Requires-Dist: mypy-boto3-transcribe<1.43.0,>=1.42.0; extra == "transcribe"
Provides-Extra: transfer
Requires-Dist: mypy-boto3-transfer<1.43.0,>=1.42.0; extra == "transfer"
Provides-Extra: translate
Requires-Dist: mypy-boto3-translate<1.43.0,>=1.42.0; extra == "translate"
Provides-Extra: trustedadvisor
Requires-Dist: mypy-boto3-trustedadvisor<1.43.0,>=1.42.0; extra == "trustedadvisor"
Provides-Extra: verifiedpermissions
Requires-Dist: mypy-boto3-verifiedpermissions<1.43.0,>=1.42.0; extra == "verifiedpermissions"
Provides-Extra: voice-id
Requires-Dist: mypy-boto3-voice-id<1.43.0,>=1.42.0; extra == "voice-id"
Provides-Extra: vpc-lattice
Requires-Dist: mypy-boto3-vpc-lattice<1.43.0,>=1.42.0; extra == "vpc-lattice"
Provides-Extra: waf
Requires-Dist: mypy-boto3-waf<1.43.0,>=1.42.0; extra == "waf"
Provides-Extra: waf-regional
Requires-Dist: mypy-boto3-waf-regional<1.43.0,>=1.42.0; extra == "waf-regional"
Provides-Extra: wafv2
Requires-Dist: mypy-boto3-wafv2<1.43.0,>=1.42.0; extra == "wafv2"
Provides-Extra: wellarchitected
Requires-Dist: mypy-boto3-wellarchitected<1.43.0,>=1.42.0; extra == "wellarchitected"
Provides-Extra: wickr
Requires-Dist: mypy-boto3-wickr<1.43.0,>=1.42.0; extra == "wickr"
Provides-Extra: wisdom
Requires-Dist: mypy-boto3-wisdom<1.43.0,>=1.42.0; extra == "wisdom"
Provides-Extra: workdocs
Requires-Dist: mypy-boto3-workdocs<1.43.0,>=1.42.0; extra == "workdocs"
Provides-Extra: workmail
Requires-Dist: mypy-boto3-workmail<1.43.0,>=1.42.0; extra == "workmail"
Provides-Extra: workmailmessageflow
Requires-Dist: mypy-boto3-workmailmessageflow<1.43.0,>=1.42.0; extra == "workmailmessageflow"
Provides-Extra: workspaces
Requires-Dist: mypy-boto3-workspaces<1.43.0,>=1.42.0; extra == "workspaces"
Provides-Extra: workspaces-instances
Requires-Dist: mypy-boto3-workspaces-instances<1.43.0,>=1.42.0; extra == "workspaces-instances"
Provides-Extra: workspaces-thin-client
Requires-Dist: mypy-boto3-workspaces-thin-client<1.43.0,>=1.42.0; extra == "workspaces-thin-client"
Provides-Extra: workspaces-web
Requires-Dist: mypy-boto3-workspaces-web<1.43.0,>=1.42.0; extra == "workspaces-web"
Provides-Extra: xray
Requires-Dist: mypy-boto3-xray<1.43.0,>=1.42.0; extra == "xray"
Dynamic: license-file
